{
  "spin": 1,
  "isEven": true,
  "color": "black",
  "number": 20,
  "isPositive": true
},
{
  "spin": 2,
  "isEven": false,
  "color": "black",
  "number": 11,
  "isPositive": true
},
{
  "spin": 3,
  "isEven": false,
  "color": "black",
  "number": 17,
  "isPositive": true
},
{
  "spin": 4,
  "isEven": true,
  "color": "red",
  "number": 12,
  "isPositive": true
},
{
  "spin": 5,
  "isEven": true,
  "color": "red",
  "number": 18,
  "isPositive": true
},
{
  "spin": 6,
  "isEven": true,
  "color": "red",
  "number": 36,
  "isPositive": true
},
{
  "spin": 7,
  "isEven": false,
  "color": "black",
  "number": 29,
  "isPositive": true
},
{
  "spin": 8,
  "isEven": true,
  "color": "black",
  "number": 4,
  "isPositive": true
},
{
  "spin": 9,
  "isEven": true,
  "color": "red",
  "number": 14,
  "isPositive": true
},
{
  "spin": 10,
  "isEven": false,
  "color": "red",
  "number": 19,
  "isPositive": true
},
{
  "spin": 11,
  "isEven": false,
  "color": "red",
  "number": 27,
  "isPositive": true
},
{
  "spin": 12,
  "isEven": false,
  "color": "red",
  "number": 21,
  "isPositive": true
},
{
  "spin": 13,
  "isEven": true,
  "color": "red",
  "number": 14,
  "isPositive": true
},
{
  "spin": 14,
  "isEven": true,
  "color": "black",
  "number": 24,
  "isPositive": true
},
{
  "spin": 15,
  "isEven": false,
  "color": "red",
  "number": 5,
  "isPositive": true
},
{
  "spin": 16,
  "isEven": true,
  "color": "black",
  "number": 22,
  "isPositive": true
},
{
  "spin": 17,
  "isEven": false,
  "color": "green",
  "number": -1,
  "isPositive": false
},
{
  "spin": 18,
  "isEven": true,
  "color": "black",
  "number": 28,
  "isPositive": true
},
{
  "spin": 19,
  "isEven": true,
  "color": "red",
  "number": 30,
  "isPositive": true
},
{
  "spin": 20,
  "isEven": true,
  "color": "red",
  "number": 18,
  "isPositive": true
},
{
  "spin": 21,
  "isEven": false,
  "color": "black",
  "number": 11,
  "isPositive": true
},
{
  "spin": 22,
  "isEven": false,
  "color": "red",
  "number": 3,
  "isPositive": true
},
{
  "spin": 23,
  "isEven": false,
  "color": "red",
  "number": 5,
  "isPositive": true
},
{
  "spin": 24,
  "isEven": true,
  "color": "black",
  "number": 6,
  "isPositive": true
},
{
  "spin": 25,
  "isEven": true,
  "color": "red",
  "number": 16,
  "isPositive": true
},
{
  "spin": 26,
  "isEven": true,
  "color": "black",
  "number": 2,
  "isPositive": true
},
{
  "spin": 27,
  "isEven": false,
  "color": "red",
  "number": 27,
  "isPositive": true
},
{
  "spin": 28,
  "isEven": true,
  "color": "red",
  "number": 36,
  "isPositive": true
},
{
  "spin": 29,
  "isEven": true,
  "color": "black",
  "number": 20,
  "isPositive": true
},
{
  "spin": 30,
  "isEven": false,
  "color": "black",
  "number": 15,
  "isPositive": true
},
{
  "spin": 31,
  "isEven": true,
  "color": "black",
  "number": 22,
  "isPositive": true
},
{
  "spin": 32,
  "isEven": false,
  "color": "black",
  "number": 31,
  "isPositive": true
},
{
  "spin": 33,
  "isEven": true,
  "color": "red",
  "number": 36,
  "isPositive": true
},
{
  "spin": 34,
  "isEven": false,
  "color": "red",
  "number": 5,
  "isPositive": true
},
{
  "spin": 35,
  "isEven": true,
  "color": "red",
  "number": 12,
  "isPositive": true
},
{
  "spin": 36,
  "isEven": true,
  "color": "red",
  "number": 32,
  "isPositive": true
},
{
  "spin": 37,
  "isEven": true,
  "color": "black",
  "number": 6,
  "isPositive": true
},
{
  "spin": 38,
  "isEven": false,
  "color": "black",
  "number": 31,
  "isPositive": true
},
{
  "spin": 39,
  "isEven": true,
  "color": "black",
  "number": 24,
  "isPositive": true
},
{
  "spin": 40,
  "isEven": false,
  "color": "black",
  "number": 31,
  "isPositive": true
},
{
  "spin": 41,
  "isEven": true,
  "color": "black",
  "number": 2,
  "isPositive": true
},
{
  "spin": 42,
  "isEven": false,
  "color": "black",
  "number": 17,
  "isPositive": true
},
{
  "spin": 43,
  "isEven": true,
  "color": "red",
  "number": 30,
  "isPositive": true
},
{
  "spin": 44,
  "isEven": false,
  "color": "black",
  "number": 13,
  "isPositive": true
},
{
  "spin": 45,
  "isEven": false,
  "color": "black",
  "number": 35,
  "isPositive": true
},
{
  "spin": 46,
  "isEven": false,
  "color": "black",
  "number": 13,
  "isPositive": true
},
{
  "spin": 47,
  "isEven": true,
  "color": "red",
  "number": 36,
  "isPositive": true
},
{
  "spin": 48,
  "isEven": false,
  "color": "green",
  "number": -1,
  "isPositive": false
},
{
  "spin": 49,
  "isEven": false,
  "color": "red",
  "number": 7,
  "isPositive": true
},
{
  "spin": 50,
  "isEven": false,
  "color": "red",
  "number": 9,
  "isPositive": true
},
{
  "spin": 51,
  "isEven": true,
  "color": "black",
  "number": 20,
  "isPositive": true
},
{
  "spin": 52,
  "isEven": false,
  "color": "red",
  "number": 3,
  "isPositive": true
},
{
  "spin": 53,
  "isEven": false,
  "color": "red",
  "number": 19,
  "isPositive": true
},
{
  "spin": 54,
  "isEven": false,
  "color": "green",
  "number": 0,
  "isPositive": false
},
{
  "spin": 55,
  "isEven": false,
  "color": "red",
  "number": 23,
  "isPositive": true
},
{
  "spin": 56,
  "isEven": false,
  "color": "red",
  "number": 5,
  "isPositive": true
},
{
  "spin": 57,
  "isEven": false,
  "color": "black",
  "number": 29,
  "isPositive": true
},
{
  "spin": 58,
  "isEven": true,
  "color": "red",
  "number": 14,
  "isPositive": true
},
{
  "spin": 59,
  "isEven": false,
  "color": "red",
  "number": 3,
  "isPositive": true
},
{
  "spin": 60,
  "isEven": true,
  "color": "black",
  "number": 28,
  "isPositive": true
},
{
  "spin": 61,
  "isEven": false,
  "color": "black",
  "number": 29,
  "isPositive": true
},
{
  "spin": 62,
  "isEven": false,
  "color": "black",
  "number": 35,
  "isPositive": true
},
{
  "spin": 63,
  "isEven": true,
  "color": "red",
  "number": 18,
  "isPositive": true
},
{
  "spin": 64,
  "isEven": true,
  "color": "black",
  "number": 28,
  "isPositive": true
},
{
  "spin": 65,
  "isEven": false,
  "color": "red",
  "number": 3,
  "isPositive": true
},
{
  "spin": 66,
  "isEven": true,
  "color": "black",
  "number": 10,
  "isPositive": true
},
{
  "spin": 67,
  "isEven": true,
  "color": "red",
  "number": 36,
  "isPositive": true
},
{
  "spin": 68,
  "isEven": true,
  "color": "red",
  "number": 30,
  "isPositive": true
},
{
  "spin": 69,
  "isEven": false,
  "color": "black",
  "number": 31,
  "isPositive": true
},
{
  "spin": 70,
  "isEven": true,
  "color": "red",
  "number": 14,
  "isPositive": true
},
{
  "spin": 71,
  "isEven": false,
  "color": "black",
  "number": 17,
  "isPositive": true
},
{
  "spin": 72,
  "isEven": true,
  "color": "red",
  "number": 32,
  "isPositive": true
},
{
  "spin": 73,
  "isEven": true,
  "color": "red",
  "number": 18,
  "isPositive": true
},
{
  "spin": 74,
  "isEven": true,
  "color": "red",
  "number": 16,
  "isPositive": true
},
{
  "spin": 75,
  "isEven": true,
  "color": "red",
  "number": 34,
  "isPositive": true
},
{
  "spin": 76,
  "isEven": false,
  "color": "black",
  "number": 15,
  "isPositive": true
},
{
  "spin": 77,
  "isEven": true,
  "color": "black",
  "number": 8,
  "isPositive": true
},
{
  "spin": 78,
  "isEven": true,
  "color": "black",
  "number": 6,
  "isPositive": true
},
{
  "spin": 79,
  "isEven": false,
  "color": "red",
  "number": 1,
  "isPositive": true
},
{
  "spin": 80,
  "isEven": true,
  "color": "black",
  "number": 4,
  "isPositive": true
},
{
  "spin": 81,
  "isEven": false,
  "color": "red",
  "number": 1,
  "isPositive": true
},
{
  "spin": 82,
  "isEven": true,
  "color": "red",
  "number": 34,
  "isPositive": true
},
{
  "spin": 83,
  "isEven": true,
  "color": "red",
  "number": 12,
  "isPositive": true
},
{
  "spin": 84,
  "isEven": true,
  "color": "black",
  "number": 4,
  "isPositive": true
},
{
  "spin": 85,
  "isEven": false,
  "color": "red",
  "number": 21,
  "isPositive": true
},
{
  "spin": 86,
  "isEven": false,
  "color": "black",
  "number": 31,
  "isPositive": true
},
{
  "spin": 87,
  "isEven": false,
  "color": "red",
  "number": 5,
  "isPositive": true
},
{
  "spin": 88,
  "isEven": true,
  "color": "black",
  "number": 4,
  "isPositive": true
},
{
  "spin": 89,
  "isEven": true,
  "color": "black",
  "number": 10,
  "isPositive": true
},
{
  "spin": 90,
  "isEven": true,
  "color": "black",
  "number": 20,
  "isPositive": true
},
{
  "spin": 91,
  "isEven": false,
  "color": "red",
  "number": 19,
  "isPositive": true
},
{
  "spin": 92,
  "isEven": true,
  "color": "black",
  "number": 2,
  "isPositive": true
},
{
  "spin": 93,
  "isEven": true,
  "color": "black",
  "number": 28,
  "isPositive": true
},
{
  "spin": 94,
  "isEven": true,
  "color": "black",
  "number": 28,
  "isPositive": true
},
{
  "spin": 95,
  "isEven": false,
  "color": "black",
  "number": 31,
  "isPositive": true
},
{
  "spin": 96,
  "isEven": false,
  "color": "red",
  "number": 9,
  "isPositive": true
},
{
  "spin": 97,
  "isEven": true,
  "color": "red",
  "number": 32,
  "isPositive": true
},
{
  "spin": 98,
  "isEven": true,
  "color": "red",
  "number": 30,
  "isPositive": true
},
{
  "spin": 99,
  "isEven": false,
  "color": "black",
  "number": 13,
  "isPositive": true
},
{
  "spin": 100,
  "isEven": true,
  "color": "black",
  "number": 8,
  "isPositive": true
},
{
  "spin": 101,
  "isEven": true,
  "color": "black",
  "number": 6,
  "isPositive": true
},
{
  "spin": 102,
  "isEven": false,
  "color": "black",
  "number": 29,
  "isPositive": true
},
{
  "spin": 103,
  "isEven": false,
  "color": "red",
  "number": 19,
  "isPositive": true
},
{
  "spin": 104,
  "isEven": false,
  "color": "black",
  "number": 33,
  "isPositive": true
},
{
  "spin": 105,
  "isEven": false,
  "color": "red",
  "number": 7,
  "isPositive": true
},
{
  "spin": 106,
  "isEven": true,
  "color": "black",
  "number": 26,
  "isPositive": true
},
{
  "spin": 107,
  "isEven": true,
  "color": "black",
  "number": 8,
  "isPositive": true
},
{
  "spin": 108,
  "isEven": false,
  "color": "red",
  "number": 9,
  "isPositive": true
},
{
  "spin": 109,
  "isEven": true,
  "color": "red",
  "number": 14,
  "isPositive": true
},
{
  "spin": 110,
  "isEven": false,
  "color": "black",
  "number": 17,
  "isPositive": true
},
{
  "spin": 111,
  "isEven": true,
  "color": "red",
  "number": 12,
  "isPositive": true
},
{
  "spin": 112,
  "isEven": false,
  "color": "black",
  "number": 35,
  "isPositive": true
},
{
  "spin": 113,
  "isEven": false,
  "color": "black",
  "number": 13,
  "isPositive": true
},
{
  "spin": 114,
  "isEven": true,
  "color": "black",
  "number": 8,
  "isPositive": true
},
{
  "spin": 115,
  "isEven": false,
  "color": "green",
  "number": 0,
  "isPositive": false
},
{
  "spin": 116,
  "isEven": false,
  "color": "red",
  "number": 19,
  "isPositive": true
},
{
  "spin": 117,
  "isEven": false,
  "color": "black",
  "number": 17,
  "isPositive": true
},
{
  "spin": 118,
  "isEven": true,
  "color": "red",
  "number": 18,
  "isPositive": true
},
{
  "spin": 119,
  "isEven": false,
  "color": "red",
  "number": 5,
  "isPositive": true
},
{
  "spin": 120,
  "isEven": true,
  "color": "red",
  "number": 32,
  "isPositive": true
},
{
  "spin": 121,
  "isEven": true,
  "color": "black",
  "number": 6,
  "isPositive": true
},
{
  "spin": 122,
  "isEven": true,
  "color": "red",
  "number": 18,
  "isPositive": true
},
{
  "spin": 123,
  "isEven": false,
  "color": "red",
  "number": 23,
  "isPositive": true
},
{
  "spin": 124,
  "isEven": true,
  "color": "black",
  "number": 4,
  "isPositive": true
},
{
  "spin": 125,
  "isEven": false,
  "color": "red",
  "number": 9,
  "isPositive": true
},
{
  "spin": 126,
  "isEven": true,
  "color": "red",
  "number": 18,
  "isPositive": true
},
{
  "spin": 127,
  "isEven": false,
  "color": "red",
  "number": 21,
  "isPositive": true
},
{
  "spin": 128,
  "isEven": false,
  "color": "black",
  "number": 11,
  "isPositive": true
},
{
  "spin": 129,
  "isEven": false,
  "color": "green",
  "number": 0,
  "isPositive": false
},
{
  "spin": 130,
  "isEven": true,
  "color": "red",
  "number": 14,
  "isPositive": true
},
{
  "spin": 131,
  "isEven": false,
  "color": "black",
  "number": 11,
  "isPositive": true
},
{
  "spin": 132,
  "isEven": false,
  "color": "black",
  "number": 17,
  "isPositive": true
},
{
  "spin": 133,
  "isEven": false,
  "color": "black",
  "number": 17,
  "isPositive": true
},
{
  "spin": 134,
  "isEven": false,
  "color": "black",
  "number": 13,
  "isPositive": true
},
{
  "spin": 135,
  "isEven": true,
  "color": "red",
  "number": 32,
  "isPositive": true
},
{
  "spin": 136,
  "isEven": false,
  "color": "red",
  "number": 19,
  "isPositive": true
},
{
  "spin": 137,
  "isEven": false,
  "color": "red",
  "number": 3,
  "isPositive": true
},
{
  "spin": 138,
  "isEven": true,
  "color": "black",
  "number": 26,
  "isPositive": true
},
{
  "spin": 139,
  "isEven": true,
  "color": "red",
  "number": 18,
  "isPositive": true
},
{
  "spin": 140,
  "isEven": false,
  "color": "red",
  "number": 21,
  "isPositive": true
},
{
  "spin": 141,
  "isEven": false,
  "color": "green",
  "number": 0,
  "isPositive": false
},
{
  "spin": 142,
  "isEven": false,
  "color": "red",
  "number": 23,
  "isPositive": true
},
{
  "spin": 143,
  "isEven": false,
  "color": "black",
  "number": 17,
  "isPositive": true
},
{
  "spin": 144,
  "isEven": true,
  "color": "black",
  "number": 6,
  "isPositive": true
},
{
  "spin": 145,
  "isEven": false,
  "color": "red",
  "number": 21,
  "isPositive": true
},
{
  "spin": 146,
  "isEven": false,
  "color": "red",
  "number": 21,
  "isPositive": true
},
{
  "spin": 147,
  "isEven": false,
  "color": "red",
  "number": 23,
  "isPositive": true
},
{
  "spin": 148,
  "isEven": true,
  "color": "black",
  "number": 26,
  "isPositive": true
},
{
  "spin": 149,
  "isEven": true,
  "color": "black",
  "number": 26,
  "isPositive": true
},
{
  "spin": 150,
  "isEven": true,
  "color": "red",
  "number": 12,
  "isPositive": true
},
{
  "spin": 151,
  "isEven": false,
  "color": "black",
  "number": 35,
  "isPositive": true
},
{
  "spin": 152,
  "isEven": false,
  "color": "red",
  "number": 5,
  "isPositive": true
},
{
  "spin": 153,
  "isEven": false,
  "color": "black",
  "number": 13,
  "isPositive": true
},
{
  "spin": 154,
  "isEven": true,
  "color": "black",
  "number": 24,
  "isPositive": true
},
{
  "spin": 155,
  "isEven": false,
  "color": "green",
  "number": -1,
  "isPositive": false
},
{
  "spin": 156,
  "isEven": false,
  "color": "red",
  "number": 23,
  "isPositive": true
},
{
  "spin": 157,
  "isEven": true,
  "color": "red",
  "number": 16,
  "isPositive": true
},
{
  "spin": 158,
  "isEven": true,
  "color": "black",
  "number": 6,
  "isPositive": true
},
{
  "spin": 159,
  "isEven": false,
  "color": "black",
  "number": 13,
  "isPositive": true
},
{
  "spin": 160,
  "isEven": false,
  "color": "black",
  "number": 29,
  "isPositive": true
},
{
  "spin": 161,
  "isEven": false,
  "color": "black",
  "number": 17,
  "isPositive": true
},
{
  "spin": 162,
  "isEven": false,
  "color": "black",
  "number": 33,
  "isPositive": true
},
{
  "spin": 163,
  "isEven": false,
  "color": "green",
  "number": 0,
  "isPositive": false
},
{
  "spin": 164,
  "isEven": true,
  "color": "black",
  "number": 22,
  "isPositive": true
},
{
  "spin": 165,
  "isEven": true,
  "color": "red",
  "number": 36,
  "isPositive": true
},
{
  "spin": 166,
  "isEven": false,
  "color": "black",
  "number": 13,
  "isPositive": true
},
{
  "spin": 167,
  "isEven": true,
  "color": "black",
  "number": 24,
  "isPositive": true
},
{
  "spin": 168,
  "isEven": true,
  "color": "red",
  "number": 32,
  "isPositive": true
},
{
  "spin": 169,
  "isEven": true,
  "color": "black",
  "number": 24,
  "isPositive": true
},
{
  "spin": 170,
  "isEven": true,
  "color": "black",
  "number": 24,
  "isPositive": true
},
{
  "spin": 171,
  "isEven": false,
  "color": "green",
  "number": -1,
  "isPositive": false
},
{
  "spin": 172,
  "isEven": false,
  "color": "red",
  "number": 21,
  "isPositive": true
},
{
  "spin": 173,
  "isEven": true,
  "color": "black",
  "number": 26,
  "isPositive": true
},
{
  "spin": 174,
  "isEven": false,
  "color": "red",
  "number": 25,
  "isPositive": true
},
{
  "spin": 175,
  "isEven": true,
  "color": "black",
  "number": 20,
  "isPositive": true
},
{
  "spin": 176,
  "isEven": false,
  "color": "red",
  "number": 5,
  "isPositive": true
},
{
  "spin": 177,
  "isEven": true,
  "color": "red",
  "number": 36,
  "isPositive": true
},
{
  "spin": 178,
  "isEven": false,
  "color": "red",
  "number": 23,
  "isPositive": true
},
{
  "spin": 179,
  "isEven": true,
  "color": "black",
  "number": 10,
  "isPositive": true
},
{
  "spin": 180,
  "isEven": false,
  "color": "red",
  "number": 3,
  "isPositive": true
},
{
  "spin": 181,
  "isEven": false,
  "color": "black",
  "number": 31,
  "isPositive": true
},
{
  "spin": 182,
  "isEven": false,
  "color": "black",
  "number": 11,
  "isPositive": true
},
{
  "spin": 183,
  "isEven": false,
  "color": "green",
  "number": 0,
  "isPositive": false
},
{
  "spin": 184,
  "isEven": true,
  "color": "red",
  "number": 30,
  "isPositive": true
},
{
  "spin": 185,
  "isEven": false,
  "color": "black",
  "number": 15,
  "isPositive": true
},
{
  "spin": 186,
  "isEven": false,
  "color": "black",
  "number": 29,
  "isPositive": true
},
{
  "spin": 187,
  "isEven": false,
  "color": "red",
  "number": 7,
  "isPositive": true
},
{
  "spin": 188,
  "isEven": true,
  "color": "red",
  "number": 34,
  "isPositive": true
},
{
  "spin": 189,
  "isEven": false,
  "color": "red",
  "number": 23,
  "isPositive": true
},
{
  "spin": 190,
  "isEven": false,
  "color": "green",
  "number": 0,
  "isPositive": false
},
{
  "spin": 191,
  "isEven": false,
  "color": "black",
  "number": 35,
  "isPositive": true
},
{
  "spin": 192,
  "isEven": false,
  "color": "red",
  "number": 9,
  "isPositive": true
},
{
  "spin": 193,
  "isEven": false,
  "color": "black",
  "number": 31,
  "isPositive": true
},
{
  "spin": 194,
  "isEven": true,
  "color": "red",
  "number": 30,
  "isPositive": true
},
{
  "spin": 195,
  "isEven": false,
  "color": "red",
  "number": 1,
  "isPositive": true
},
{
  "spin": 196,
  "isEven": false,
  "color": "red",
  "number": 5,
  "isPositive": true
},
{
  "spin": 197,
  "isEven": true,
  "color": "red",
  "number": 16,
  "isPositive": true
},
{
  "spin": 198,
  "isEven": false,
  "color": "red",
  "number": 9,
  "isPositive": true
},
{
  "spin": 199,
  "isEven": true,
  "color": "red",
  "number": 36,
  "isPositive": true
},
{
  "spin": 200,
  "isEven": false,
  "color": "red",
  "number": 21,
  "isPositive": true
},
{
  "spin": 201,
  "isEven": false,
  "color": "red",
  "number": 19,
  "isPositive": true
},
{
  "spin": 202,
  "isEven": true,
  "color": "red",
  "number": 36,
  "isPositive": true
},
{
  "spin": 203,
  "isEven": false,
  "color": "green",
  "number": -1,
  "isPositive": false
},
{
  "spin": 204,
  "isEven": true,
  "color": "red",
  "number": 14,
  "isPositive": true
},
{
  "spin": 205,
  "isEven": false,
  "color": "black",
  "number": 31,
  "isPositive": true
},
{
  "spin": 206,
  "isEven": false,
  "color": "black",
  "number": 33,
  "isPositive": true
},
{
  "spin": 207,
  "isEven": false,
  "color": "red",
  "number": 27,
  "isPositive": true
},
{
  "spin": 208,
  "isEven": true,
  "color": "black",
  "number": 6,
  "isPositive": true
},
{
  "spin": 209,
  "isEven": false,
  "color": "red",
  "number": 1,
  "isPositive": true
},
{
  "spin": 210,
  "isEven": false,
  "color": "red",
  "number": 27,
  "isPositive": true
},
{
  "spin": 211,
  "isEven": false,
  "color": "black",
  "number": 29,
  "isPositive": true
},
{
  "spin": 212,
  "isEven": true,
  "color": "black",
  "number": 10,
  "isPositive": true
},
{
  "spin": 213,
  "isEven": true,
  "color": "black",
  "number": 28,
  "isPositive": true
},
{
  "spin": 214,
  "isEven": true,
  "color": "black",
  "number": 4,
  "isPositive": true
},
{
  "spin": 215,
  "isEven": true,
  "color": "black",
  "number": 8,
  "isPositive": true
},
{
  "spin": 216,
  "isEven": true,
  "color": "black",
  "number": 2,
  "isPositive": true
},
{
  "spin": 217,
  "isEven": false,
  "color": "red",
  "number": 23,
  "isPositive": true
},
{
  "spin": 218,
  "isEven": false,
  "color": "red",
  "number": 1,
  "isPositive": true
},
{
  "spin": 219,
  "isEven": false,
  "color": "black",
  "number": 31,
  "isPositive": true
},
{
  "spin": 220,
  "isEven": false,
  "color": "black",
  "number": 29,
  "isPositive": true
},
{
  "spin": 221,
  "isEven": false,
  "color": "black",
  "number": 17,
  "isPositive": true
},
{
  "spin": 222,
  "isEven": false,
  "color": "black",
  "number": 33,
  "isPositive": true
},
{
  "spin": 223,
  "isEven": true,
  "color": "red",
  "number": 18,
  "isPositive": true
},
{
  "spin": 224,
  "isEven": true,
  "color": "black",
  "number": 6,
  "isPositive": true
},
{
  "spin": 225,
  "isEven": false,
  "color": "black",
  "number": 11,
  "isPositive": true
},
{
  "spin": 226,
  "isEven": true,
  "color": "red",
  "number": 32,
  "isPositive": true
},
{
  "spin": 227,
  "isEven": false,
  "color": "black",
  "number": 15,
  "isPositive": true
},
{
  "spin": 228,
  "isEven": false,
  "color": "red",
  "number": 9,
  "isPositive": true
},
{
  "spin": 229,
  "isEven": false,
  "color": "black",
  "number": 35,
  "isPositive": true
},
{
  "spin": 230,
  "isEven": false,
  "color": "black",
  "number": 29,
  "isPositive": true
},
{
  "spin": 231,
  "isEven": false,
  "color": "black",
  "number": 17,
  "isPositive": true
},
{
  "spin": 232,
  "isEven": true,
  "color": "red",
  "number": 16,
  "isPositive": true
},
{
  "spin": 233,
  "isEven": false,
  "color": "red",
  "number": 19,
  "isPositive": true
},
{
  "spin": 234,
  "isEven": false,
  "color": "green",
  "number": -1,
  "isPositive": false
},
{
  "spin": 235,
  "isEven": false,
  "color": "green",
  "number": 0,
  "isPositive": false
},
{
  "spin": 236,
  "isEven": true,
  "color": "black",
  "number": 8,
  "isPositive": true
},
{
  "spin": 237,
  "isEven": true,
  "color": "black",
  "number": 6,
  "isPositive": true
},
{
  "spin": 238,
  "isEven": false,
  "color": "red",
  "number": 19,
  "isPositive": true
},
{
  "spin": 239,
  "isEven": false,
  "color": "black",
  "number": 33,
  "isPositive": true
},
{
  "spin": 240,
  "isEven": false,
  "color": "red",
  "number": 19,
  "isPositive": true
},
{
  "spin": 241,
  "isEven": true,
  "color": "black",
  "number": 8,
  "isPositive": true
},
{
  "spin": 242,
  "isEven": true,
  "color": "black",
  "number": 6,
  "isPositive": true
},
{
  "spin": 243,
  "isEven": true,
  "color": "black",
  "number": 6,
  "isPositive": true
},
{
  "spin": 244,
  "isEven": true,
  "color": "red",
  "number": 14,
  "isPositive": true
},
{
  "spin": 245,
  "isEven": false,
  "color": "black",
  "number": 11,
  "isPositive": true
},
{
  "spin": 246,
  "isEven": false,
  "color": "red",
  "number": 7,
  "isPositive": true
},
{
  "spin": 247,
  "isEven": false,
  "color": "black",
  "number": 13,
  "isPositive": true
},
{
  "spin": 248,
  "isEven": false,
  "color": "black",
  "number": 29,
  "isPositive": true
},
{
  "spin": 249,
  "isEven": false,
  "color": "red",
  "number": 7,
  "isPositive": true
},
{
  "spin": 250,
  "isEven": true,
  "color": "black",
  "number": 8,
  "isPositive": true
},
{
  "spin": 251,
  "isEven": true,
  "color": "red",
  "number": 32,
  "isPositive": true
},
{
  "spin": 252,
  "isEven": false,
  "color": "black",
  "number": 15,
  "isPositive": true
},
{
  "spin": 253,
  "isEven": false,
  "color": "red",
  "number": 25,
  "isPositive": true
},
{
  "spin": 254,
  "isEven": true,
  "color": "black",
  "number": 24,
  "isPositive": true
},
{
  "spin": 255,
  "isEven": true,
  "color": "black",
  "number": 26,
  "isPositive": true
},
{
  "spin": 256,
  "isEven": false,
  "color": "black",
  "number": 31,
  "isPositive": true
},
{
  "spin": 257,
  "isEven": true,
  "color": "black",
  "number": 10,
  "isPositive": true
},
{
  "spin": 258,
  "isEven": false,
  "color": "black",
  "number": 11,
  "isPositive": true
},
{
  "spin": 259,
  "isEven": false,
  "color": "red",
  "number": 5,
  "isPositive": true
},
{
  "spin": 260,
  "isEven": false,
  "color": "black",
  "number": 15,
  "isPositive": true
},
{
  "spin": 261,
  "isEven": true,
  "color": "black",
  "number": 10,
  "isPositive": true
},
{
  "spin": 262,
  "isEven": true,
  "color": "black",
  "number": 6,
  "isPositive": true
},
{
  "spin": 263,
  "isEven": false,
  "color": "black",
  "number": 35,
  "isPositive": true
},
{
  "spin": 264,
  "isEven": false,
  "color": "black",
  "number": 29,
  "isPositive": true
},
{
  "spin": 265,
  "isEven": false,
  "color": "red",
  "number": 19,
  "isPositive": true
},
{
  "spin": 266,
  "isEven": false,
  "color": "black",
  "number": 13,
  "isPositive": true
},
{
  "spin": 267,
  "isEven": true,
  "color": "black",
  "number": 8,
  "isPositive": true
},
{
  "spin": 268,
  "isEven": true,
  "color": "black",
  "number": 20,
  "isPositive": true
},
{
  "spin": 269,
  "isEven": false,
  "color": "black",
  "number": 33,
  "isPositive": true
},
{
  "spin": 270,
  "isEven": false,
  "color": "green",
  "number": 0,
  "isPositive": false
},
{
  "spin": 271,
  "isEven": true,
  "color": "black",
  "number": 8,
  "isPositive": true
},
{
  "spin": 272,
  "isEven": true,
  "color": "red",
  "number": 36,
  "isPositive": true
},
{
  "spin": 273,
  "isEven": true,
  "color": "red",
  "number": 14,
  "isPositive": true
},
{
  "spin": 274,
  "isEven": true,
  "color": "black",
  "number": 4,
  "isPositive": true
},
{
  "spin": 275,
  "isEven": true,
  "color": "red",
  "number": 36,
  "isPositive": true
},
{
  "spin": 276,
  "isEven": true,
  "color": "red",
  "number": 14,
  "isPositive": true
},
{
  "spin": 277,
  "isEven": true,
  "color": "black",
  "number": 8,
  "isPositive": true
},
{
  "spin": 278,
  "isEven": true,
  "color": "black",
  "number": 8,
  "isPositive": true
},
{
  "spin": 279,
  "isEven": true,
  "color": "black",
  "number": 6,
  "isPositive": true
},
{
  "spin": 280,
  "isEven": true,
  "color": "red",
  "number": 18,
  "isPositive": true
},
{
  "spin": 281,
  "isEven": false,
  "color": "red",
  "number": 3,
  "isPositive": true
},
{
  "spin": 282,
  "isEven": false,
  "color": "red",
  "number": 3,
  "isPositive": true
},
{
  "spin": 283,
  "isEven": false,
  "color": "green",
  "number": -1,
  "isPositive": false
},
{
  "spin": 284,
  "isEven": false,
  "color": "red",
  "number": 27,
  "isPositive": true
},
{
  "spin": 285,
  "isEven": false,
  "color": "black",
  "number": 15,
  "isPositive": true
},
{
  "spin": 286,
  "isEven": true,
  "color": "black",
  "number": 26,
  "isPositive": true
},
{
  "spin": 287,
  "isEven": false,
  "color": "red",
  "number": 19,
  "isPositive": true
},
{
  "spin": 288,
  "isEven": true,
  "color": "black",
  "number": 6,
  "isPositive": true
},
{
  "spin": 289,
  "isEven": false,
  "color": "red",
  "number": 3,
  "isPositive": true
},
{
  "spin": 290,
  "isEven": false,
  "color": "red",
  "number": 27,
  "isPositive": true
},
{
  "spin": 291,
  "isEven": false,
  "color": "black",
  "number": 13,
  "isPositive": true
},
{
  "spin": 292,
  "isEven": true,
  "color": "black",
  "number": 6,
  "isPositive": true
},
{
  "spin": 293,
  "isEven": false,
  "color": "red",
  "number": 5,
  "isPositive": true
},
{
  "spin": 294,
  "isEven": true,
  "color": "black",
  "number": 20,
  "isPositive": true
},
{
  "spin": 295,
  "isEven": true,
  "color": "black",
  "number": 8,
  "isPositive": true
},
{
  "spin": 296,
  "isEven": true,
  "color": "black",
  "number": 8,
  "isPositive": true
},
{
  "spin": 297,
  "isEven": false,
  "color": "red",
  "number": 19,
  "isPositive": true
},
{
  "spin": 298,
  "isEven": false,
  "color": "black",
  "number": 33,
  "isPositive": true
},
{
  "spin": 299,
  "isEven": true,
  "color": "black",
  "number": 10,
  "isPositive": true
},
{
  "spin": 300,
  "isEven": false,
  "color": "black",
  "number": 11,
  "isPositive": true
},
{
  "spin": 301,
  "isEven": true,
  "color": "black",
  "number": 20,
  "isPositive": true
},
{
  "spin": 302,
  "isEven": false,
  "color": "black",
  "number": 11,
  "isPositive": true
},
{
  "spin": 303,
  "isEven": false,
  "color": "red",
  "number": 19,
  "isPositive": true
},
{
  "spin": 304,
  "isEven": true,
  "color": "black",
  "number": 28,
  "isPositive": true
},
{
  "spin": 305,
  "isEven": true,
  "color": "red",
  "number": 36,
  "isPositive": true
},
{
  "spin": 306,
  "isEven": true,
  "color": "black",
  "number": 8,
  "isPositive": true
},
{
  "spin": 307,
  "isEven": true,
  "color": "red",
  "number": 30,
  "isPositive": true
},
{
  "spin": 308,
  "isEven": true,
  "color": "red",
  "number": 14,
  "isPositive": true
},
{
  "spin": 309,
  "isEven": true,
  "color": "red",
  "number": 18,
  "isPositive": true
},
{
  "spin": 310,
  "isEven": true,
  "color": "red",
  "number": 14,
  "isPositive": true
},
{
  "spin": 311,
  "isEven": true,
  "color": "black",
  "number": 28,
  "isPositive": true
},
{
  "spin": 312,
  "isEven": false,
  "color": "black",
  "number": 13,
  "isPositive": true
},
{
  "spin": 313,
  "isEven": false,
  "color": "red",
  "number": 1,
  "isPositive": true
},
{
  "spin": 314,
  "isEven": true,
  "color": "black",
  "number": 6,
  "isPositive": true
},
{
  "spin": 315,
  "isEven": true,
  "color": "red",
  "number": 16,
  "isPositive": true
},
{
  "spin": 316,
  "isEven": false,
  "color": "red",
  "number": 5,
  "isPositive": true
},
{
  "spin": 317,
  "isEven": true,
  "color": "red",
  "number": 14,
  "isPositive": true
},
{
  "spin": 318,
  "isEven": true,
  "color": "black",
  "number": 4,
  "isPositive": true
},
{
  "spin": 319,
  "isEven": false,
  "color": "black",
  "number": 15,
  "isPositive": true
},
{
  "spin": 320,
  "isEven": false,
  "color": "black",
  "number": 29,
  "isPositive": true
},
{
  "spin": 321,
  "isEven": false,
  "color": "red",
  "number": 23,
  "isPositive": true
},
{
  "spin": 322,
  "isEven": true,
  "color": "red",
  "number": 36,
  "isPositive": true
},
{
  "spin": 323,
  "isEven": false,
  "color": "red",
  "number": 21,
  "isPositive": true
},
{
  "spin": 324,
  "isEven": false,
  "color": "black",
  "number": 15,
  "isPositive": true
},
{
  "spin": 325,
  "isEven": true,
  "color": "red",
  "number": 34,
  "isPositive": true
},
{
  "spin": 326,
  "isEven": false,
  "color": "red",
  "number": 27,
  "isPositive": true
},
{
  "spin": 327,
  "isEven": false,
  "color": "red",
  "number": 19,
  "isPositive": true
},
{
  "spin": 328,
  "isEven": false,
  "color": "red",
  "number": 3,
  "isPositive": true
},
{
  "spin": 329,
  "isEven": false,
  "color": "red",
  "number": 9,
  "isPositive": true
},
{
  "spin": 330,
  "isEven": false,
  "color": "red",
  "number": 19,
  "isPositive": true
},
{
  "spin": 331,
  "isEven": false,
  "color": "red",
  "number": 25,
  "isPositive": true
},
{
  "spin": 332,
  "isEven": true,
  "color": "black",
  "number": 4,
  "isPositive": true
},
{
  "spin": 333,
  "isEven": false,
  "color": "black",
  "number": 35,
  "isPositive": true
},
{
  "spin": 334,
  "isEven": false,
  "color": "black",
  "number": 33,
  "isPositive": true
},
{
  "spin": 335,
  "isEven": true,
  "color": "red",
  "number": 16,
  "isPositive": true
},
{
  "spin": 336,
  "isEven": true,
  "color": "red",
  "number": 30,
  "isPositive": true
},
{
  "spin": 337,
  "isEven": false,
  "color": "red",
  "number": 27,
  "isPositive": true
},
{
  "spin": 338,
  "isEven": false,
  "color": "red",
  "number": 21,
  "isPositive": true
},
{
  "spin": 339,
  "isEven": false,
  "color": "black",
  "number": 15,
  "isPositive": true
},
{
  "spin": 340,
  "isEven": false,
  "color": "black",
  "number": 17,
  "isPositive": true
},
{
  "spin": 341,
  "isEven": true,
  "color": "red",
  "number": 34,
  "isPositive": true
},
{
  "spin": 342,
  "isEven": false,
  "color": "black",
  "number": 13,
  "isPositive": true
},
{
  "spin": 343,
  "isEven": false,
  "color": "black",
  "number": 11,
  "isPositive": true
},
{
  "spin": 344,
  "isEven": false,
  "color": "red",
  "number": 1,
  "isPositive": true
},
{
  "spin": 345,
  "isEven": true,
  "color": "red",
  "number": 14,
  "isPositive": true
},
{
  "spin": 346,
  "isEven": false,
  "color": "black",
  "number": 31,
  "isPositive": true
},
{
  "spin": 347,
  "isEven": false,
  "color": "red",
  "number": 5,
  "isPositive": true
},
{
  "spin": 348,
  "isEven": true,
  "color": "black",
  "number": 2,
  "isPositive": true
},
{
  "spin": 349,
  "isEven": true,
  "color": "red",
  "number": 36,
  "isPositive": true
},
{
  "spin": 350,
  "isEven": false,
  "color": "red",
  "number": 19,
  "isPositive": true
},
{
  "spin": 351,
  "isEven": true,
  "color": "black",
  "number": 10,
  "isPositive": true
},
{
  "spin": 352,
  "isEven": true,
  "color": "red",
  "number": 34,
  "isPositive": true
},
{
  "spin": 353,
  "isEven": true,
  "color": "red",
  "number": 34,
  "isPositive": true
},
{
  "spin": 354,
  "isEven": true,
  "color": "black",
  "number": 22,
  "isPositive": true
},
{
  "spin": 355,
  "isEven": false,
  "color": "red",
  "number": 5,
  "isPositive": true
},
{
  "spin": 356,
  "isEven": false,
  "color": "red",
  "number": 21,
  "isPositive": true
},
{
  "spin": 357,
  "isEven": false,
  "color": "red",
  "number": 21,
  "isPositive": true
},
{
  "spin": 358,
  "isEven": false,
  "color": "red",
  "number": 7,
  "isPositive": true
},
{
  "spin": 359,
  "isEven": false,
  "color": "green",
  "number": 0,
  "isPositive": false
},
{
  "spin": 360,
  "isEven": true,
  "color": "red",
  "number": 12,
  "isPositive": true
},
{
  "spin": 361,
  "isEven": true,
  "color": "red",
  "number": 36,
  "isPositive": true
},
{
  "spin": 362,
  "isEven": false,
  "color": "black",
  "number": 33,
  "isPositive": true
},
{
  "spin": 363,
  "isEven": false,
  "color": "black",
  "number": 15,
  "isPositive": true
},
{
  "spin": 364,
  "isEven": false,
  "color": "black",
  "number": 35,
  "isPositive": true
},
{
  "spin": 365,
  "isEven": true,
  "color": "black",
  "number": 2,
  "isPositive": true
},
{
  "spin": 366,
  "isEven": false,
  "color": "black",
  "number": 11,
  "isPositive": true
},
{
  "spin": 367,
  "isEven": false,
  "color": "green",
  "number": -1,
  "isPositive": false
},
{
  "spin": 368,
  "isEven": true,
  "color": "black",
  "number": 22,
  "isPositive": true
},
{
  "spin": 369,
  "isEven": false,
  "color": "black",
  "number": 13,
  "isPositive": true
},
{
  "spin": 370,
  "isEven": false,
  "color": "black",
  "number": 17,
  "isPositive": true
},
{
  "spin": 371,
  "isEven": true,
  "color": "red",
  "number": 32,
  "isPositive": true
},
{
  "spin": 372,
  "isEven": false,
  "color": "black",
  "number": 13,
  "isPositive": true
},
{
  "spin": 373,
  "isEven": true,
  "color": "black",
  "number": 20,
  "isPositive": true
},
{
  "spin": 374,
  "isEven": true,
  "color": "black",
  "number": 2,
  "isPositive": true
},
{
  "spin": 375,
  "isEven": false,
  "color": "red",
  "number": 7,
  "isPositive": true
},
{
  "spin": 376,
  "isEven": false,
  "color": "black",
  "number": 17,
  "isPositive": true
},
{
  "spin": 377,
  "isEven": true,
  "color": "black",
  "number": 24,
  "isPositive": true
},
{
  "spin": 378,
  "isEven": false,
  "color": "green",
  "number": 0,
  "isPositive": false
},
{
  "spin": 379,
  "isEven": true,
  "color": "black",
  "number": 4,
  "isPositive": true
},
{
  "spin": 380,
  "isEven": true,
  "color": "black",
  "number": 26,
  "isPositive": true
},
{
  "spin": 381,
  "isEven": false,
  "color": "red",
  "number": 9,
  "isPositive": true
},
{
  "spin": 382,
  "isEven": true,
  "color": "red",
  "number": 34,
  "isPositive": true
},
{
  "spin": 383,
  "isEven": false,
  "color": "red",
  "number": 27,
  "isPositive": true
},
{
  "spin": 384,
  "isEven": true,
  "color": "black",
  "number": 4,
  "isPositive": true
},
{
  "spin": 385,
  "isEven": false,
  "color": "red",
  "number": 19,
  "isPositive": true
},
{
  "spin": 386,
  "isEven": true,
  "color": "black",
  "number": 22,
  "isPositive": true
},
{
  "spin": 387,
  "isEven": false,
  "color": "red",
  "number": 9,
  "isPositive": true
},
{
  "spin": 388,
  "isEven": true,
  "color": "red",
  "number": 32,
  "isPositive": true
},
{
  "spin": 389,
  "isEven": false,
  "color": "black",
  "number": 33,
  "isPositive": true
},
{
  "spin": 390,
  "isEven": false,
  "color": "red",
  "number": 21,
  "isPositive": true
},
{
  "spin": 391,
  "isEven": false,
  "color": "black",
  "number": 17,
  "isPositive": true
},
{
  "spin": 392,
  "isEven": false,
  "color": "black",
  "number": 15,
  "isPositive": true
},
{
  "spin": 393,
  "isEven": false,
  "color": "green",
  "number": 0,
  "isPositive": false
},
{
  "spin": 394,
  "isEven": true,
  "color": "black",
  "number": 24,
  "isPositive": true
},
{
  "spin": 395,
  "isEven": false,
  "color": "red",
  "number": 27,
  "isPositive": true
},
{
  "spin": 396,
  "isEven": false,
  "color": "red",
  "number": 9,
  "isPositive": true
},
{
  "spin": 397,
  "isEven": true,
  "color": "red",
  "number": 14,
  "isPositive": true
},
{
  "spin": 398,
  "isEven": false,
  "color": "black",
  "number": 13,
  "isPositive": true
},
{
  "spin": 399,
  "isEven": true,
  "color": "red",
  "number": 16,
  "isPositive": true
},
{
  "spin": 400,
  "isEven": true,
  "color": "red",
  "number": 36,
  "isPositive": true
},
{
  "spin": 401,
  "isEven": true,
  "color": "red",
  "number": 14,
  "isPositive": true
},
{
  "spin": 402,
  "isEven": false,
  "color": "red",
  "number": 3,
  "isPositive": true
},
{
  "spin": 403,
  "isEven": false,
  "color": "red",
  "number": 27,
  "isPositive": true
},
{
  "spin": 404,
  "isEven": false,
  "color": "red",
  "number": 27,
  "isPositive": true
},
{
  "spin": 405,
  "isEven": true,
  "color": "black",
  "number": 10,
  "isPositive": true
},
{
  "spin": 406,
  "isEven": true,
  "color": "red",
  "number": 12,
  "isPositive": true
},
{
  "spin": 407,
  "isEven": true,
  "color": "black",
  "number": 28,
  "isPositive": true
},
{
  "spin": 408,
  "isEven": false,
  "color": "black",
  "number": 35,
  "isPositive": true
},
{
  "spin": 409,
  "isEven": false,
  "color": "black",
  "number": 35,
  "isPositive": true
},
{
  "spin": 410,
  "isEven": false,
  "color": "red",
  "number": 5,
  "isPositive": true
},
{
  "spin": 411,
  "isEven": true,
  "color": "black",
  "number": 28,
  "isPositive": true
},
{
  "spin": 412,
  "isEven": true,
  "color": "red",
  "number": 34,
  "isPositive": true
},
{
  "spin": 413,
  "isEven": false,
  "color": "red",
  "number": 21,
  "isPositive": true
},
{
  "spin": 414,
  "isEven": true,
  "color": "black",
  "number": 20,
  "isPositive": true
},
{
  "spin": 415,
  "isEven": false,
  "color": "black",
  "number": 15,
  "isPositive": true
},
{
  "spin": 416,
  "isEven": true,
  "color": "black",
  "number": 22,
  "isPositive": true
},
{
  "spin": 417,
  "isEven": true,
  "color": "black",
  "number": 20,
  "isPositive": true
},
{
  "spin": 418,
  "isEven": true,
  "color": "red",
  "number": 36,
  "isPositive": true
},
{
  "spin": 419,
  "isEven": true,
  "color": "red",
  "number": 30,
  "isPositive": true
},
{
  "spin": 420,
  "isEven": false,
  "color": "red",
  "number": 9,
  "isPositive": true
},
{
  "spin": 421,
  "isEven": true,
  "color": "black",
  "number": 10,
  "isPositive": true
},
{
  "spin": 422,
  "isEven": false,
  "color": "red",
  "number": 9,
  "isPositive": true
},
{
  "spin": 423,
  "isEven": false,
  "color": "red",
  "number": 3,
  "isPositive": true
},
{
  "spin": 424,
  "isEven": false,
  "color": "red",
  "number": 25,
  "isPositive": true
},
{
  "spin": 425,
  "isEven": false,
  "color": "black",
  "number": 11,
  "isPositive": true
},
{
  "spin": 426,
  "isEven": true,
  "color": "red",
  "number": 12,
  "isPositive": true
},
{
  "spin": 427,
  "isEven": false,
  "color": "red",
  "number": 19,
  "isPositive": true
},
{
  "spin": 428,
  "isEven": true,
  "color": "black",
  "number": 20,
  "isPositive": true
},
{
  "spin": 429,
  "isEven": false,
  "color": "black",
  "number": 17,
  "isPositive": true
},
{
  "spin": 430,
  "isEven": false,
  "color": "black",
  "number": 35,
  "isPositive": true
},
{
  "spin": 431,
  "isEven": false,
  "color": "green",
  "number": -1,
  "isPositive": false
},
{
  "spin": 432,
  "isEven": false,
  "color": "black",
  "number": 11,
  "isPositive": true
},
{
  "spin": 433,
  "isEven": true,
  "color": "red",
  "number": 14,
  "isPositive": true
},
{
  "spin": 434,
  "isEven": false,
  "color": "red",
  "number": 19,
  "isPositive": true
},
{
  "spin": 435,
  "isEven": false,
  "color": "black",
  "number": 15,
  "isPositive": true
},
{
  "spin": 436,
  "isEven": true,
  "color": "red",
  "number": 16,
  "isPositive": true
},
{
  "spin": 437,
  "isEven": false,
  "color": "black",
  "number": 31,
  "isPositive": true
},
{
  "spin": 438,
  "isEven": true,
  "color": "black",
  "number": 8,
  "isPositive": true
},
{
  "spin": 439,
  "isEven": true,
  "color": "black",
  "number": 2,
  "isPositive": true
},
{
  "spin": 440,
  "isEven": false,
  "color": "red",
  "number": 7,
  "isPositive": true
},
{
  "spin": 441,
  "isEven": false,
  "color": "black",
  "number": 35,
  "isPositive": true
},
{
  "spin": 442,
  "isEven": true,
  "color": "black",
  "number": 20,
  "isPositive": true
},
{
  "spin": 443,
  "isEven": false,
  "color": "red",
  "number": 9,
  "isPositive": true
},
{
  "spin": 444,
  "isEven": true,
  "color": "red",
  "number": 12,
  "isPositive": true
},
{
  "spin": 445,
  "isEven": false,
  "color": "red",
  "number": 21,
  "isPositive": true
},
{
  "spin": 446,
  "isEven": false,
  "color": "green",
  "number": 0,
  "isPositive": false
},
{
  "spin": 447,
  "isEven": true,
  "color": "black",
  "number": 20,
  "isPositive": true
},
{
  "spin": 448,
  "isEven": false,
  "color": "black",
  "number": 29,
  "isPositive": true
},
{
  "spin": 449,
  "isEven": true,
  "color": "red",
  "number": 30,
  "isPositive": true
},
{
  "spin": 450,
  "isEven": true,
  "color": "black",
  "number": 24,
  "isPositive": true
},
{
  "spin": 451,
  "isEven": false,
  "color": "black",
  "number": 17,
  "isPositive": true
},
{
  "spin": 452,
  "isEven": false,
  "color": "red",
  "number": 7,
  "isPositive": true
},
{
  "spin": 453,
  "isEven": true,
  "color": "black",
  "number": 22,
  "isPositive": true
},
{
  "spin": 454,
  "isEven": false,
  "color": "red",
  "number": 3,
  "isPositive": true
},
{
  "spin": 455,
  "isEven": true,
  "color": "black",
  "number": 4,
  "isPositive": true
},
{
  "spin": 456,
  "isEven": true,
  "color": "red",
  "number": 36,
  "isPositive": true
},
{
  "spin": 457,
  "isEven": true,
  "color": "black",
  "number": 26,
  "isPositive": true
},
{
  "spin": 458,
  "isEven": false,
  "color": "red",
  "number": 25,
  "isPositive": true
},
{
  "spin": 459,
  "isEven": true,
  "color": "red",
  "number": 30,
  "isPositive": true
},
{
  "spin": 460,
  "isEven": false,
  "color": "red",
  "number": 19,
  "isPositive": true
},
{
  "spin": 461,
  "isEven": true,
  "color": "red",
  "number": 18,
  "isPositive": true
},
{
  "spin": 462,
  "isEven": true,
  "color": "black",
  "number": 22,
  "isPositive": true
},
{
  "spin": 463,
  "isEven": true,
  "color": "black",
  "number": 26,
  "isPositive": true
},
{
  "spin": 464,
  "isEven": true,
  "color": "black",
  "number": 28,
  "isPositive": true
},
{
  "spin": 465,
  "isEven": true,
  "color": "red",
  "number": 14,
  "isPositive": true
},
{
  "spin": 466,
  "isEven": true,
  "color": "red",
  "number": 12,
  "isPositive": true
},
{
  "spin": 467,
  "isEven": false,
  "color": "black",
  "number": 33,
  "isPositive": true
},
{
  "spin": 468,
  "isEven": false,
  "color": "black",
  "number": 17,
  "isPositive": true
},
{
  "spin": 469,
  "isEven": false,
  "color": "red",
  "number": 7,
  "isPositive": true
},
{
  "spin": 470,
  "isEven": false,
  "color": "green",
  "number": -1,
  "isPositive": false
},
{
  "spin": 471,
  "isEven": false,
  "color": "red",
  "number": 3,
  "isPositive": true
},
{
  "spin": 472,
  "isEven": true,
  "color": "red",
  "number": 36,
  "isPositive": true
},
{
  "spin": 473,
  "isEven": true,
  "color": "black",
  "number": 10,
  "isPositive": true
},
{
  "spin": 474,
  "isEven": false,
  "color": "red",
  "number": 7,
  "isPositive": true
},
{
  "spin": 475,
  "isEven": false,
  "color": "black",
  "number": 17,
  "isPositive": true
},
{
  "spin": 476,
  "isEven": true,
  "color": "black",
  "number": 4,
  "isPositive": true
},
{
  "spin": 477,
  "isEven": false,
  "color": "black",
  "number": 31,
  "isPositive": true
},
{
  "spin": 478,
  "isEven": true,
  "color": "black",
  "number": 2,
  "isPositive": true
},
{
  "spin": 479,
  "isEven": false,
  "color": "green",
  "number": 0,
  "isPositive": false
},
{
  "spin": 480,
  "isEven": true,
  "color": "black",
  "number": 10,
  "isPositive": true
},
{
  "spin": 481,
  "isEven": false,
  "color": "red",
  "number": 19,
  "isPositive": true
},
{
  "spin": 482,
  "isEven": true,
  "color": "red",
  "number": 30,
  "isPositive": true
},
{
  "spin": 483,
  "isEven": true,
  "color": "black",
  "number": 10,
  "isPositive": true
},
{
  "spin": 484,
  "isEven": true,
  "color": "red",
  "number": 16,
  "isPositive": true
},
{
  "spin": 485,
  "isEven": false,
  "color": "red",
  "number": 1,
  "isPositive": true
},
{
  "spin": 486,
  "isEven": true,
  "color": "black",
  "number": 26,
  "isPositive": true
},
{
  "spin": 487,
  "isEven": true,
  "color": "red",
  "number": 30,
  "isPositive": true
},
{
  "spin": 488,
  "isEven": true,
  "color": "red",
  "number": 30,
  "isPositive": true
},
{
  "spin": 489,
  "isEven": false,
  "color": "black",
  "number": 13,
  "isPositive": true
},
{
  "spin": 490,
  "isEven": true,
  "color": "black",
  "number": 2,
  "isPositive": true
},
{
  "spin": 491,
  "isEven": false,
  "color": "black",
  "number": 17,
  "isPositive": true
},
{
  "spin": 492,
  "isEven": false,
  "color": "red",
  "number": 5,
  "isPositive": true
},
{
  "spin": 493,
  "isEven": true,
  "color": "black",
  "number": 6,
  "isPositive": true
},
{
  "spin": 494,
  "isEven": true,
  "color": "red",
  "number": 36,
  "isPositive": true
},
{
  "spin": 495,
  "isEven": false,
  "color": "red",
  "number": 23,
  "isPositive": true
},
{
  "spin": 496,
  "isEven": true,
  "color": "black",
  "number": 20,
  "isPositive": true
},
{
  "spin": 497,
  "isEven": false,
  "color": "red",
  "number": 7,
  "isPositive": true
},
{
  "spin": 498,
  "isEven": true,
  "color": "red",
  "number": 34,
  "isPositive": true
},
{
  "spin": 499,
  "isEven": true,
  "color": "black",
  "number": 8,
  "isPositive": true
},
{
  "spin": 500,
  "isEven": false,
  "color": "red",
  "number": 23,
  "isPositive": true
},
{
  "spin": 501,
  "isEven": true,
  "color": "red",
  "number": 14,
  "isPositive": true
},
{
  "spin": 502,
  "isEven": true,
  "color": "black",
  "number": 2,
  "isPositive": true
},
{
  "spin": 503,
  "isEven": false,
  "color": "red",
  "number": 3,
  "isPositive": true
},
{
  "spin": 504,
  "isEven": true,
  "color": "black",
  "number": 6,
  "isPositive": true
},
{
  "spin": 505,
  "isEven": false,
  "color": "black",
  "number": 31,
  "isPositive": true
},
{
  "spin": 506,
  "isEven": true,
  "color": "black",
  "number": 22,
  "isPositive": true
},
{
  "spin": 507,
  "isEven": true,
  "color": "red",
  "number": 16,
  "isPositive": true
},
{
  "spin": 508,
  "isEven": false,
  "color": "red",
  "number": 3,
  "isPositive": true
},
{
  "spin": 509,
  "isEven": false,
  "color": "green",
  "number": 0,
  "isPositive": false
},
{
  "spin": 510,
  "isEven": true,
  "color": "black",
  "number": 2,
  "isPositive": true
},
{
  "spin": 511,
  "isEven": true,
  "color": "red",
  "number": 32,
  "isPositive": true
},
{
  "spin": 512,
  "isEven": false,
  "color": "black",
  "number": 29,
  "isPositive": true
},
{
  "spin": 513,
  "isEven": true,
  "color": "black",
  "number": 28,
  "isPositive": true
},
{
  "spin": 514,
  "isEven": false,
  "color": "red",
  "number": 25,
  "isPositive": true
},
{
  "spin": 515,
  "isEven": true,
  "color": "black",
  "number": 20,
  "isPositive": true
},
{
  "spin": 516,
  "isEven": false,
  "color": "black",
  "number": 33,
  "isPositive": true
},
{
  "spin": 517,
  "isEven": true,
  "color": "black",
  "number": 4,
  "isPositive": true
},
{
  "spin": 518,
  "isEven": false,
  "color": "red",
  "number": 1,
  "isPositive": true
},
{
  "spin": 519,
  "isEven": false,
  "color": "red",
  "number": 5,
  "isPositive": true
},
{
  "spin": 520,
  "isEven": false,
  "color": "red",
  "number": 19,
  "isPositive": true
},
{
  "spin": 521,
  "isEven": false,
  "color": "black",
  "number": 29,
  "isPositive": true
},
{
  "spin": 522,
  "isEven": true,
  "color": "black",
  "number": 2,
  "isPositive": true
},
{
  "spin": 523,
  "isEven": false,
  "color": "red",
  "number": 21,
  "isPositive": true
},
{
  "spin": 524,
  "isEven": true,
  "color": "black",
  "number": 24,
  "isPositive": true
},
{
  "spin": 525,
  "isEven": false,
  "color": "black",
  "number": 13,
  "isPositive": true
},
{
  "spin": 526,
  "isEven": false,
  "color": "black",
  "number": 15,
  "isPositive": true
},
{
  "spin": 527,
  "isEven": false,
  "color": "red",
  "number": 3,
  "isPositive": true
},
{
  "spin": 528,
  "isEven": false,
  "color": "red",
  "number": 21,
  "isPositive": true
},
{
  "spin": 529,
  "isEven": false,
  "color": "black",
  "number": 35,
  "isPositive": true
},
{
  "spin": 530,
  "isEven": true,
  "color": "black",
  "number": 24,
  "isPositive": true
},
{
  "spin": 531,
  "isEven": true,
  "color": "black",
  "number": 20,
  "isPositive": true
},
{
  "spin": 532,
  "isEven": false,
  "color": "black",
  "number": 31,
  "isPositive": true
},
{
  "spin": 533,
  "isEven": true,
  "color": "black",
  "number": 8,
  "isPositive": true
},
{
  "spin": 534,
  "isEven": true,
  "color": "black",
  "number": 22,
  "isPositive": true
},
{
  "spin": 535,
  "isEven": false,
  "color": "red",
  "number": 3,
  "isPositive": true
},
{
  "spin": 536,
  "isEven": false,
  "color": "red",
  "number": 27,
  "isPositive": true
},
{
  "spin": 537,
  "isEven": false,
  "color": "black",
  "number": 31,
  "isPositive": true
},
{
  "spin": 538,
  "isEven": true,
  "color": "black",
  "number": 8,
  "isPositive": true
},
{
  "spin": 539,
  "isEven": true,
  "color": "black",
  "number": 24,
  "isPositive": true
},
{
  "spin": 540,
  "isEven": false,
  "color": "red",
  "number": 3,
  "isPositive": true
},
{
  "spin": 541,
  "isEven": true,
  "color": "black",
  "number": 4,
  "isPositive": true
},
{
  "spin": 542,
  "isEven": false,
  "color": "black",
  "number": 13,
  "isPositive": true
},
{
  "spin": 543,
  "isEven": false,
  "color": "black",
  "number": 29,
  "isPositive": true
},
{
  "spin": 544,
  "isEven": true,
  "color": "black",
  "number": 10,
  "isPositive": true
},
{
  "spin": 545,
  "isEven": true,
  "color": "red",
  "number": 12,
  "isPositive": true
},
{
  "spin": 546,
  "isEven": true,
  "color": "black",
  "number": 22,
  "isPositive": true
},
{
  "spin": 547,
  "isEven": true,
  "color": "black",
  "number": 20,
  "isPositive": true
},
{
  "spin": 548,
  "isEven": false,
  "color": "red",
  "number": 23,
  "isPositive": true
},
{
  "spin": 549,
  "isEven": false,
  "color": "red",
  "number": 27,
  "isPositive": true
},
{
  "spin": 550,
  "isEven": false,
  "color": "red",
  "number": 1,
  "isPositive": true
},
{
  "spin": 551,
  "isEven": false,
  "color": "red",
  "number": 19,
  "isPositive": true
},
{
  "spin": 552,
  "isEven": true,
  "color": "black",
  "number": 6,
  "isPositive": true
},
{
  "spin": 553,
  "isEven": false,
  "color": "black",
  "number": 13,
  "isPositive": true
},
{
  "spin": 554,
  "isEven": true,
  "color": "red",
  "number": 18,
  "isPositive": true
},
{
  "spin": 555,
  "isEven": true,
  "color": "red",
  "number": 32,
  "isPositive": true
},
{
  "spin": 556,
  "isEven": false,
  "color": "black",
  "number": 13,
  "isPositive": true
},
{
  "spin": 557,
  "isEven": false,
  "color": "green",
  "number": 0,
  "isPositive": false
},
{
  "spin": 558,
  "isEven": false,
  "color": "green",
  "number": 0,
  "isPositive": false
},
{
  "spin": 559,
  "isEven": true,
  "color": "black",
  "number": 24,
  "isPositive": true
},
{
  "spin": 560,
  "isEven": false,
  "color": "red",
  "number": 27,
  "isPositive": true
},
{
  "spin": 561,
  "isEven": true,
  "color": "black",
  "number": 28,
  "isPositive": true
},
{
  "spin": 562,
  "isEven": true,
  "color": "red",
  "number": 12,
  "isPositive": true
},
{
  "spin": 563,
  "isEven": true,
  "color": "red",
  "number": 14,
  "isPositive": true
},
{
  "spin": 564,
  "isEven": false,
  "color": "black",
  "number": 29,
  "isPositive": true
},
{
  "spin": 565,
  "isEven": true,
  "color": "black",
  "number": 20,
  "isPositive": true
},
{
  "spin": 566,
  "isEven": false,
  "color": "red",
  "number": 1,
  "isPositive": true
},
{
  "spin": 567,
  "isEven": true,
  "color": "black",
  "number": 24,
  "isPositive": true
},
{
  "spin": 568,
  "isEven": true,
  "color": "black",
  "number": 10,
  "isPositive": true
},
{
  "spin": 569,
  "isEven": true,
  "color": "red",
  "number": 12,
  "isPositive": true
},
{
  "spin": 570,
  "isEven": true,
  "color": "black",
  "number": 24,
  "isPositive": true
},
{
  "spin": 571,
  "isEven": true,
  "color": "red",
  "number": 32,
  "isPositive": true
},
{
  "spin": 572,
  "isEven": false,
  "color": "red",
  "number": 27,
  "isPositive": true
},
{
  "spin": 573,
  "isEven": true,
  "color": "black",
  "number": 22,
  "isPositive": true
},
{
  "spin": 574,
  "isEven": false,
  "color": "red",
  "number": 1,
  "isPositive": true
},
{
  "spin": 575,
  "isEven": false,
  "color": "red",
  "number": 1,
  "isPositive": true
},
{
  "spin": 576,
  "isEven": false,
  "color": "black",
  "number": 15,
  "isPositive": true
},
{
  "spin": 577,
  "isEven": false,
  "color": "red",
  "number": 27,
  "isPositive": true
},
{
  "spin": 578,
  "isEven": false,
  "color": "black",
  "number": 35,
  "isPositive": true
},
{
  "spin": 579,
  "isEven": true,
  "color": "red",
  "number": 36,
  "isPositive": true
},
{
  "spin": 580,
  "isEven": true,
  "color": "red",
  "number": 16,
  "isPositive": true
},
{
  "spin": 581,
  "isEven": true,
  "color": "black",
  "number": 6,
  "isPositive": true
},
{
  "spin": 582,
  "isEven": false,
  "color": "black",
  "number": 15,
  "isPositive": true
},
{
  "spin": 583,
  "isEven": true,
  "color": "red",
  "number": 14,
  "isPositive": true
},
{
  "spin": 584,
  "isEven": false,
  "color": "black",
  "number": 13,
  "isPositive": true
},
{
  "spin": 585,
  "isEven": true,
  "color": "black",
  "number": 4,
  "isPositive": true
},
{
  "spin": 586,
  "isEven": true,
  "color": "red",
  "number": 36,
  "isPositive": true
},
{
  "spin": 587,
  "isEven": false,
  "color": "red",
  "number": 9,
  "isPositive": true
},
{
  "spin": 588,
  "isEven": false,
  "color": "red",
  "number": 27,
  "isPositive": true
},
{
  "spin": 589,
  "isEven": true,
  "color": "black",
  "number": 28,
  "isPositive": true
},
{
  "spin": 590,
  "isEven": true,
  "color": "black",
  "number": 6,
  "isPositive": true
},
{
  "spin": 591,
  "isEven": false,
  "color": "red",
  "number": 27,
  "isPositive": true
},
{
  "spin": 592,
  "isEven": false,
  "color": "black",
  "number": 35,
  "isPositive": true
},
{
  "spin": 593,
  "isEven": true,
  "color": "red",
  "number": 16,
  "isPositive": true
},
{
  "spin": 594,
  "isEven": false,
  "color": "red",
  "number": 1,
  "isPositive": true
},
{
  "spin": 595,
  "isEven": true,
  "color": "red",
  "number": 14,
  "isPositive": true
},
{
  "spin": 596,
  "isEven": true,
  "color": "red",
  "number": 30,
  "isPositive": true
},
{
  "spin": 597,
  "isEven": false,
  "color": "red",
  "number": 25,
  "isPositive": true
},
{
  "spin": 598,
  "isEven": true,
  "color": "black",
  "number": 4,
  "isPositive": true
},
{
  "spin": 599,
  "isEven": true,
  "color": "black",
  "number": 8,
  "isPositive": true
},
{
  "spin": 600,
  "isEven": true,
  "color": "red",
  "number": 34,
  "isPositive": true
},
{
  "spin": 601,
  "isEven": true,
  "color": "red",
  "number": 36,
  "isPositive": true
},
{
  "spin": 602,
  "isEven": false,
  "color": "red",
  "number": 21,
  "isPositive": true
},
{
  "spin": 603,
  "isEven": false,
  "color": "red",
  "number": 9,
  "isPositive": true
},
{
  "spin": 604,
  "isEven": false,
  "color": "green",
  "number": -1,
  "isPositive": false
},
{
  "spin": 605,
  "isEven": false,
  "color": "red",
  "number": 19,
  "isPositive": true
},
{
  "spin": 606,
  "isEven": true,
  "color": "black",
  "number": 10,
  "isPositive": true
},
{
  "spin": 607,
  "isEven": false,
  "color": "green",
  "number": 0,
  "isPositive": false
},
{
  "spin": 608,
  "isEven": true,
  "color": "black",
  "number": 22,
  "isPositive": true
},
{
  "spin": 609,
  "isEven": true,
  "color": "black",
  "number": 4,
  "isPositive": true
},
{
  "spin": 610,
  "isEven": false,
  "color": "red",
  "number": 3,
  "isPositive": true
},
{
  "spin": 611,
  "isEven": false,
  "color": "black",
  "number": 33,
  "isPositive": true
},
{
  "spin": 612,
  "isEven": true,
  "color": "red",
  "number": 16,
  "isPositive": true
},
{
  "spin": 613,
  "isEven": false,
  "color": "green",
  "number": -1,
  "isPositive": false
},
{
  "spin": 614,
  "isEven": false,
  "color": "black",
  "number": 11,
  "isPositive": true
},
{
  "spin": 615,
  "isEven": true,
  "color": "red",
  "number": 16,
  "isPositive": true
},
{
  "spin": 616,
  "isEven": true,
  "color": "red",
  "number": 32,
  "isPositive": true
},
{
  "spin": 617,
  "isEven": false,
  "color": "red",
  "number": 5,
  "isPositive": true
},
{
  "spin": 618,
  "isEven": true,
  "color": "red",
  "number": 36,
  "isPositive": true
},
{
  "spin": 619,
  "isEven": false,
  "color": "red",
  "number": 27,
  "isPositive": true
},
{
  "spin": 620,
  "isEven": true,
  "color": "black",
  "number": 20,
  "isPositive": true
},
{
  "spin": 621,
  "isEven": true,
  "color": "black",
  "number": 20,
  "isPositive": true
},
{
  "spin": 622,
  "isEven": true,
  "color": "black",
  "number": 6,
  "isPositive": true
},
{
  "spin": 623,
  "isEven": false,
  "color": "black",
  "number": 15,
  "isPositive": true
},
{
  "spin": 624,
  "isEven": true,
  "color": "red",
  "number": 36,
  "isPositive": true
},
{
  "spin": 625,
  "isEven": false,
  "color": "black",
  "number": 35,
  "isPositive": true
},
{
  "spin": 626,
  "isEven": true,
  "color": "black",
  "number": 24,
  "isPositive": true
},
{
  "spin": 627,
  "isEven": true,
  "color": "red",
  "number": 32,
  "isPositive": true
},
{
  "spin": 628,
  "isEven": false,
  "color": "black",
  "number": 13,
  "isPositive": true
},
{
  "spin": 629,
  "isEven": false,
  "color": "red",
  "number": 3,
  "isPositive": true
},
{
  "spin": 630,
  "isEven": false,
  "color": "red",
  "number": 19,
  "isPositive": true
},
{
  "spin": 631,
  "isEven": true,
  "color": "red",
  "number": 14,
  "isPositive": true
},
{
  "spin": 632,
  "isEven": true,
  "color": "black",
  "number": 22,
  "isPositive": true
},
{
  "spin": 633,
  "isEven": false,
  "color": "red",
  "number": 7,
  "isPositive": true
},
{
  "spin": 634,
  "isEven": true,
  "color": "black",
  "number": 24,
  "isPositive": true
},
{
  "spin": 635,
  "isEven": true,
  "color": "red",
  "number": 12,
  "isPositive": true
},
{
  "spin": 636,
  "isEven": true,
  "color": "black",
  "number": 6,
  "isPositive": true
},
{
  "spin": 637,
  "isEven": false,
  "color": "green",
  "number": -1,
  "isPositive": false
},
{
  "spin": 638,
  "isEven": false,
  "color": "red",
  "number": 21,
  "isPositive": true
},
{
  "spin": 639,
  "isEven": false,
  "color": "red",
  "number": 23,
  "isPositive": true
},
{
  "spin": 640,
  "isEven": false,
  "color": "red",
  "number": 19,
  "isPositive": true
},
{
  "spin": 641,
  "isEven": true,
  "color": "red",
  "number": 34,
  "isPositive": true
},
{
  "spin": 642,
  "isEven": false,
  "color": "black",
  "number": 11,
  "isPositive": true
},
{
  "spin": 643,
  "isEven": true,
  "color": "red",
  "number": 34,
  "isPositive": true
},
{
  "spin": 644,
  "isEven": false,
  "color": "red",
  "number": 27,
  "isPositive": true
},
{
  "spin": 645,
  "isEven": true,
  "color": "black",
  "number": 20,
  "isPositive": true
},
{
  "spin": 646,
  "isEven": false,
  "color": "red",
  "number": 9,
  "isPositive": true
},
{
  "spin": 647,
  "isEven": false,
  "color": "black",
  "number": 29,
  "isPositive": true
},
{
  "spin": 648,
  "isEven": true,
  "color": "red",
  "number": 32,
  "isPositive": true
},
{
  "spin": 649,
  "isEven": true,
  "color": "black",
  "number": 10,
  "isPositive": true
},
{
  "spin": 650,
  "isEven": false,
  "color": "red",
  "number": 3,
  "isPositive": true
},
{
  "spin": 651,
  "isEven": true,
  "color": "black",
  "number": 22,
  "isPositive": true
},
{
  "spin": 652,
  "isEven": true,
  "color": "red",
  "number": 36,
  "isPositive": true
},
{
  "spin": 653,
  "isEven": true,
  "color": "red",
  "number": 30,
  "isPositive": true
},
{
  "spin": 654,
  "isEven": true,
  "color": "black",
  "number": 10,
  "isPositive": true
},
{
  "spin": 655,
  "isEven": true,
  "color": "red",
  "number": 30,
  "isPositive": true
},
{
  "spin": 656,
  "isEven": false,
  "color": "green",
  "number": 0,
  "isPositive": false
},
{
  "spin": 657,
  "isEven": false,
  "color": "black",
  "number": 35,
  "isPositive": true
},
{
  "spin": 658,
  "isEven": true,
  "color": "red",
  "number": 30,
  "isPositive": true
},
{
  "spin": 659,
  "isEven": false,
  "color": "black",
  "number": 31,
  "isPositive": true
},
{
  "spin": 660,
  "isEven": true,
  "color": "red",
  "number": 30,
  "isPositive": true
},
{
  "spin": 661,
  "isEven": false,
  "color": "black",
  "number": 31,
  "isPositive": true
},
{
  "spin": 662,
  "isEven": false,
  "color": "red",
  "number": 5,
  "isPositive": true
},
{
  "spin": 663,
  "isEven": false,
  "color": "black",
  "number": 29,
  "isPositive": true
},
{
  "spin": 664,
  "isEven": true,
  "color": "black",
  "number": 26,
  "isPositive": true
},
{
  "spin": 665,
  "isEven": true,
  "color": "red",
  "number": 34,
  "isPositive": true
},
{
  "spin": 666,
  "isEven": true,
  "color": "black",
  "number": 28,
  "isPositive": true
},
{
  "spin": 667,
  "isEven": true,
  "color": "red",
  "number": 32,
  "isPositive": true
},
{
  "spin": 668,
  "isEven": true,
  "color": "red",
  "number": 12,
  "isPositive": true
},
{
  "spin": 669,
  "isEven": true,
  "color": "red",
  "number": 18,
  "isPositive": true
},
{
  "spin": 670,
  "isEven": true,
  "color": "black",
  "number": 26,
  "isPositive": true
},
{
  "spin": 671,
  "isEven": false,
  "color": "red",
  "number": 9,
  "isPositive": true
},
{
  "spin": 672,
  "isEven": false,
  "color": "red",
  "number": 5,
  "isPositive": true
},
{
  "spin": 673,
  "isEven": false,
  "color": "black",
  "number": 11,
  "isPositive": true
},
{
  "spin": 674,
  "isEven": false,
  "color": "red",
  "number": 19,
  "isPositive": true
},
{
  "spin": 675,
  "isEven": false,
  "color": "black",
  "number": 31,
  "isPositive": true
},
{
  "spin": 676,
  "isEven": false,
  "color": "green",
  "number": 0,
  "isPositive": false
},
{
  "spin": 677,
  "isEven": false,
  "color": "black",
  "number": 33,
  "isPositive": true
},
{
  "spin": 678,
  "isEven": true,
  "color": "red",
  "number": 18,
  "isPositive": true
},
{
  "spin": 679,
  "isEven": true,
  "color": "black",
  "number": 6,
  "isPositive": true
},
{
  "spin": 680,
  "isEven": false,
  "color": "black",
  "number": 17,
  "isPositive": true
},
{
  "spin": 681,
  "isEven": true,
  "color": "black",
  "number": 28,
  "isPositive": true
},
{
  "spin": 682,
  "isEven": false,
  "color": "black",
  "number": 31,
  "isPositive": true
},
{
  "spin": 683,
  "isEven": false,
  "color": "black",
  "number": 11,
  "isPositive": true
},
{
  "spin": 684,
  "isEven": false,
  "color": "black",
  "number": 31,
  "isPositive": true
},
{
  "spin": 685,
  "isEven": true,
  "color": "black",
  "number": 2,
  "isPositive": true
},
{
  "spin": 686,
  "isEven": true,
  "color": "red",
  "number": 18,
  "isPositive": true
},
{
  "spin": 687,
  "isEven": true,
  "color": "black",
  "number": 24,
  "isPositive": true
},
{
  "spin": 688,
  "isEven": false,
  "color": "red",
  "number": 7,
  "isPositive": true
},
{
  "spin": 689,
  "isEven": true,
  "color": "red",
  "number": 34,
  "isPositive": true
},
{
  "spin": 690,
  "isEven": true,
  "color": "black",
  "number": 20,
  "isPositive": true
},
{
  "spin": 691,
  "isEven": true,
  "color": "black",
  "number": 20,
  "isPositive": true
},
{
  "spin": 692,
  "isEven": false,
  "color": "green",
  "number": -1,
  "isPositive": false
},
{
  "spin": 693,
  "isEven": true,
  "color": "black",
  "number": 6,
  "isPositive": true
},
{
  "spin": 694,
  "isEven": true,
  "color": "black",
  "number": 2,
  "isPositive": true
},
{
  "spin": 695,
  "isEven": true,
  "color": "red",
  "number": 34,
  "isPositive": true
},
{
  "spin": 696,
  "isEven": false,
  "color": "red",
  "number": 7,
  "isPositive": true
},
{
  "spin": 697,
  "isEven": false,
  "color": "black",
  "number": 17,
  "isPositive": true
},
{
  "spin": 698,
  "isEven": false,
  "color": "black",
  "number": 31,
  "isPositive": true
},
{
  "spin": 699,
  "isEven": false,
  "color": "red",
  "number": 19,
  "isPositive": true
},
{
  "spin": 700,
  "isEven": false,
  "color": "black",
  "number": 15,
  "isPositive": true
},
{
  "spin": 701,
  "isEven": false,
  "color": "green",
  "number": -1,
  "isPositive": false
},
{
  "spin": 702,
  "isEven": false,
  "color": "red",
  "number": 25,
  "isPositive": true
},
{
  "spin": 703,
  "isEven": false,
  "color": "red",
  "number": 3,
  "isPositive": true
},
{
  "spin": 704,
  "isEven": true,
  "color": "red",
  "number": 16,
  "isPositive": true
},
{
  "spin": 705,
  "isEven": true,
  "color": "black",
  "number": 4,
  "isPositive": true
},
{
  "spin": 706,
  "isEven": false,
  "color": "green",
  "number": 0,
  "isPositive": false
},
{
  "spin": 707,
  "isEven": true,
  "color": "red",
  "number": 12,
  "isPositive": true
},
{
  "spin": 708,
  "isEven": false,
  "color": "black",
  "number": 35,
  "isPositive": true
},
{
  "spin": 709,
  "isEven": true,
  "color": "red",
  "number": 18,
  "isPositive": true
},
{
  "spin": 710,
  "isEven": true,
  "color": "black",
  "number": 26,
  "isPositive": true
},
{
  "spin": 711,
  "isEven": true,
  "color": "red",
  "number": 16,
  "isPositive": true
},
{
  "spin": 712,
  "isEven": false,
  "color": "black",
  "number": 11,
  "isPositive": true
},
{
  "spin": 713,
  "isEven": false,
  "color": "green",
  "number": -1,
  "isPositive": false
},
{
  "spin": 714,
  "isEven": true,
  "color": "red",
  "number": 14,
  "isPositive": true
},
{
  "spin": 715,
  "isEven": false,
  "color": "black",
  "number": 15,
  "isPositive": true
},
{
  "spin": 716,
  "isEven": false,
  "color": "black",
  "number": 33,
  "isPositive": true
},
{
  "spin": 717,
  "isEven": false,
  "color": "black",
  "number": 15,
  "isPositive": true
},
{
  "spin": 718,
  "isEven": false,
  "color": "red",
  "number": 25,
  "isPositive": true
},
{
  "spin": 719,
  "isEven": true,
  "color": "black",
  "number": 24,
  "isPositive": true
},
{
  "spin": 720,
  "isEven": false,
  "color": "red",
  "number": 9,
  "isPositive": true
},
{
  "spin": 721,
  "isEven": false,
  "color": "black",
  "number": 29,
  "isPositive": true
},
{
  "spin": 722,
  "isEven": true,
  "color": "red",
  "number": 16,
  "isPositive": true
},
{
  "spin": 723,
  "isEven": false,
  "color": "red",
  "number": 7,
  "isPositive": true
},
{
  "spin": 724,
  "isEven": true,
  "color": "red",
  "number": 14,
  "isPositive": true
},
{
  "spin": 725,
  "isEven": true,
  "color": "black",
  "number": 10,
  "isPositive": true
},
{
  "spin": 726,
  "isEven": false,
  "color": "red",
  "number": 27,
  "isPositive": true
},
{
  "spin": 727,
  "isEven": false,
  "color": "red",
  "number": 21,
  "isPositive": true
},
{
  "spin": 728,
  "isEven": false,
  "color": "red",
  "number": 23,
  "isPositive": true
},
{
  "spin": 729,
  "isEven": true,
  "color": "black",
  "number": 26,
  "isPositive": true
},
{
  "spin": 730,
  "isEven": true,
  "color": "red",
  "number": 16,
  "isPositive": true
},
{
  "spin": 731,
  "isEven": false,
  "color": "red",
  "number": 21,
  "isPositive": true
},
{
  "spin": 732,
  "isEven": true,
  "color": "black",
  "number": 20,
  "isPositive": true
},
{
  "spin": 733,
  "isEven": false,
  "color": "black",
  "number": 13,
  "isPositive": true
},
{
  "spin": 734,
  "isEven": true,
  "color": "black",
  "number": 4,
  "isPositive": true
},
{
  "spin": 735,
  "isEven": false,
  "color": "red",
  "number": 21,
  "isPositive": true
},
{
  "spin": 736,
  "isEven": false,
  "color": "red",
  "number": 5,
  "isPositive": true
},
{
  "spin": 737,
  "isEven": false,
  "color": "black",
  "number": 11,
  "isPositive": true
},
{
  "spin": 738,
  "isEven": false,
  "color": "red",
  "number": 7,
  "isPositive": true
},
{
  "spin": 739,
  "isEven": true,
  "color": "red",
  "number": 34,
  "isPositive": true
},
{
  "spin": 740,
  "isEven": true,
  "color": "black",
  "number": 6,
  "isPositive": true
},
{
  "spin": 741,
  "isEven": false,
  "color": "black",
  "number": 13,
  "isPositive": true
},
{
  "spin": 742,
  "isEven": true,
  "color": "black",
  "number": 28,
  "isPositive": true
},
{
  "spin": 743,
  "isEven": true,
  "color": "red",
  "number": 36,
  "isPositive": true
},
{
  "spin": 744,
  "isEven": true,
  "color": "black",
  "number": 22,
  "isPositive": true
},
{
  "spin": 745,
  "isEven": false,
  "color": "red",
  "number": 5,
  "isPositive": true
},
{
  "spin": 746,
  "isEven": true,
  "color": "black",
  "number": 6,
  "isPositive": true
},
{
  "spin": 747,
  "isEven": false,
  "color": "black",
  "number": 15,
  "isPositive": true
},
{
  "spin": 748,
  "isEven": false,
  "color": "black",
  "number": 11,
  "isPositive": true
},
{
  "spin": 749,
  "isEven": true,
  "color": "black",
  "number": 26,
  "isPositive": true
},
{
  "spin": 750,
  "isEven": true,
  "color": "red",
  "number": 34,
  "isPositive": true
},
{
  "spin": 751,
  "isEven": false,
  "color": "red",
  "number": 21,
  "isPositive": true
},
{
  "spin": 752,
  "isEven": false,
  "color": "red",
  "number": 1,
  "isPositive": true
},
{
  "spin": 753,
  "isEven": false,
  "color": "red",
  "number": 19,
  "isPositive": true
},
{
  "spin": 754,
  "isEven": true,
  "color": "red",
  "number": 12,
  "isPositive": true
},
{
  "spin": 755,
  "isEven": false,
  "color": "red",
  "number": 23,
  "isPositive": true
},
{
  "spin": 756,
  "isEven": false,
  "color": "red",
  "number": 7,
  "isPositive": true
},
{
  "spin": 757,
  "isEven": false,
  "color": "red",
  "number": 9,
  "isPositive": true
},
{
  "spin": 758,
  "isEven": true,
  "color": "black",
  "number": 2,
  "isPositive": true
},
{
  "spin": 759,
  "isEven": true,
  "color": "red",
  "number": 32,
  "isPositive": true
},
{
  "spin": 760,
  "isEven": false,
  "color": "red",
  "number": 23,
  "isPositive": true
},
{
  "spin": 761,
  "isEven": false,
  "color": "black",
  "number": 17,
  "isPositive": true
},
{
  "spin": 762,
  "isEven": false,
  "color": "red",
  "number": 1,
  "isPositive": true
},
{
  "spin": 763,
  "isEven": true,
  "color": "red",
  "number": 34,
  "isPositive": true
},
{
  "spin": 764,
  "isEven": false,
  "color": "red",
  "number": 23,
  "isPositive": true
},
{
  "spin": 765,
  "isEven": false,
  "color": "black",
  "number": 29,
  "isPositive": true
},
{
  "spin": 766,
  "isEven": false,
  "color": "green",
  "number": -1,
  "isPositive": false
},
{
  "spin": 767,
  "isEven": true,
  "color": "black",
  "number": 8,
  "isPositive": true
},
{
  "spin": 768,
  "isEven": true,
  "color": "black",
  "number": 24,
  "isPositive": true
},
{
  "spin": 769,
  "isEven": true,
  "color": "red",
  "number": 12,
  "isPositive": true
},
{
  "spin": 770,
  "isEven": true,
  "color": "black",
  "number": 2,
  "isPositive": true
},
{
  "spin": 771,
  "isEven": false,
  "color": "red",
  "number": 27,
  "isPositive": true
},
{
  "spin": 772,
  "isEven": false,
  "color": "black",
  "number": 13,
  "isPositive": true
},
{
  "spin": 773,
  "isEven": true,
  "color": "black",
  "number": 10,
  "isPositive": true
},
{
  "spin": 774,
  "isEven": true,
  "color": "red",
  "number": 14,
  "isPositive": true
},
{
  "spin": 775,
  "isEven": false,
  "color": "red",
  "number": 1,
  "isPositive": true
},
{
  "spin": 776,
  "isEven": false,
  "color": "red",
  "number": 21,
  "isPositive": true
},
{
  "spin": 777,
  "isEven": false,
  "color": "red",
  "number": 27,
  "isPositive": true
},
{
  "spin": 778,
  "isEven": false,
  "color": "black",
  "number": 13,
  "isPositive": true
},
{
  "spin": 779,
  "isEven": true,
  "color": "red",
  "number": 12,
  "isPositive": true
},
{
  "spin": 780,
  "isEven": true,
  "color": "red",
  "number": 16,
  "isPositive": true
},
{
  "spin": 781,
  "isEven": true,
  "color": "red",
  "number": 12,
  "isPositive": true
},
{
  "spin": 782,
  "isEven": false,
  "color": "red",
  "number": 23,
  "isPositive": true
},
{
  "spin": 783,
  "isEven": false,
  "color": "black",
  "number": 29,
  "isPositive": true
},
{
  "spin": 784,
  "isEven": false,
  "color": "red",
  "number": 27,
  "isPositive": true
},
{
  "spin": 785,
  "isEven": false,
  "color": "red",
  "number": 7,
  "isPositive": true
},
{
  "spin": 786,
  "isEven": true,
  "color": "red",
  "number": 36,
  "isPositive": true
},
{
  "spin": 787,
  "isEven": true,
  "color": "red",
  "number": 30,
  "isPositive": true
},
{
  "spin": 788,
  "isEven": false,
  "color": "black",
  "number": 17,
  "isPositive": true
},
{
  "spin": 789,
  "isEven": false,
  "color": "red",
  "number": 5,
  "isPositive": true
},
{
  "spin": 790,
  "isEven": false,
  "color": "black",
  "number": 33,
  "isPositive": true
},
{
  "spin": 791,
  "isEven": false,
  "color": "red",
  "number": 7,
  "isPositive": true
},
{
  "spin": 792,
  "isEven": false,
  "color": "black",
  "number": 11,
  "isPositive": true
},
{
  "spin": 793,
  "isEven": false,
  "color": "black",
  "number": 15,
  "isPositive": true
},
{
  "spin": 794,
  "isEven": true,
  "color": "black",
  "number": 28,
  "isPositive": true
},
{
  "spin": 795,
  "isEven": false,
  "color": "black",
  "number": 15,
  "isPositive": true
},
{
  "spin": 796,
  "isEven": false,
  "color": "black",
  "number": 35,
  "isPositive": true
},
{
  "spin": 797,
  "isEven": false,
  "color": "green",
  "number": 0,
  "isPositive": false
},
{
  "spin": 798,
  "isEven": true,
  "color": "black",
  "number": 6,
  "isPositive": true
},
{
  "spin": 799,
  "isEven": false,
  "color": "red",
  "number": 9,
  "isPositive": true
},
{
  "spin": 800,
  "isEven": true,
  "color": "black",
  "number": 8,
  "isPositive": true
},
{
  "spin": 801,
  "isEven": false,
  "color": "red",
  "number": 7,
  "isPositive": true
},
{
  "spin": 802,
  "isEven": true,
  "color": "red",
  "number": 16,
  "isPositive": true
},
{
  "spin": 803,
  "isEven": true,
  "color": "red",
  "number": 34,
  "isPositive": true
},
{
  "spin": 804,
  "isEven": true,
  "color": "red",
  "number": 14,
  "isPositive": true
},
{
  "spin": 805,
  "isEven": true,
  "color": "black",
  "number": 4,
  "isPositive": true
},
{
  "spin": 806,
  "isEven": false,
  "color": "red",
  "number": 27,
  "isPositive": true
},
{
  "spin": 807,
  "isEven": false,
  "color": "red",
  "number": 3,
  "isPositive": true
},
{
  "spin": 808,
  "isEven": false,
  "color": "green",
  "number": -1,
  "isPositive": false
},
{
  "spin": 809,
  "isEven": false,
  "color": "black",
  "number": 13,
  "isPositive": true
},
{
  "spin": 810,
  "isEven": true,
  "color": "black",
  "number": 22,
  "isPositive": true
},
{
  "spin": 811,
  "isEven": false,
  "color": "red",
  "number": 3,
  "isPositive": true
},
{
  "spin": 812,
  "isEven": true,
  "color": "red",
  "number": 32,
  "isPositive": true
},
{
  "spin": 813,
  "isEven": false,
  "color": "red",
  "number": 27,
  "isPositive": true
},
{
  "spin": 814,
  "isEven": true,
  "color": "black",
  "number": 28,
  "isPositive": true
},
{
  "spin": 815,
  "isEven": true,
  "color": "black",
  "number": 28,
  "isPositive": true
},
{
  "spin": 816,
  "isEven": true,
  "color": "black",
  "number": 24,
  "isPositive": true
},
{
  "spin": 817,
  "isEven": true,
  "color": "black",
  "number": 22,
  "isPositive": true
},
{
  "spin": 818,
  "isEven": true,
  "color": "black",
  "number": 10,
  "isPositive": true
},
{
  "spin": 819,
  "isEven": true,
  "color": "red",
  "number": 36,
  "isPositive": true
},
{
  "spin": 820,
  "isEven": true,
  "color": "red",
  "number": 32,
  "isPositive": true
},
{
  "spin": 821,
  "isEven": true,
  "color": "black",
  "number": 10,
  "isPositive": true
},
{
  "spin": 822,
  "isEven": true,
  "color": "red",
  "number": 30,
  "isPositive": true
},
{
  "spin": 823,
  "isEven": true,
  "color": "black",
  "number": 22,
  "isPositive": true
},
{
  "spin": 824,
  "isEven": false,
  "color": "black",
  "number": 15,
  "isPositive": true
},
{
  "spin": 825,
  "isEven": true,
  "color": "red",
  "number": 36,
  "isPositive": true
},
{
  "spin": 826,
  "isEven": true,
  "color": "black",
  "number": 20,
  "isPositive": true
},
{
  "spin": 827,
  "isEven": true,
  "color": "red",
  "number": 32,
  "isPositive": true
},
{
  "spin": 828,
  "isEven": false,
  "color": "red",
  "number": 25,
  "isPositive": true
},
{
  "spin": 829,
  "isEven": true,
  "color": "black",
  "number": 6,
  "isPositive": true
},
{
  "spin": 830,
  "isEven": false,
  "color": "red",
  "number": 3,
  "isPositive": true
},
{
  "spin": 831,
  "isEven": false,
  "color": "red",
  "number": 5,
  "isPositive": true
},
{
  "spin": 832,
  "isEven": false,
  "color": "black",
  "number": 33,
  "isPositive": true
},
{
  "spin": 833,
  "isEven": true,
  "color": "black",
  "number": 28,
  "isPositive": true
},
{
  "spin": 834,
  "isEven": false,
  "color": "red",
  "number": 7,
  "isPositive": true
},
{
  "spin": 835,
  "isEven": true,
  "color": "black",
  "number": 20,
  "isPositive": true
},
{
  "spin": 836,
  "isEven": false,
  "color": "red",
  "number": 25,
  "isPositive": true
},
{
  "spin": 837,
  "isEven": true,
  "color": "black",
  "number": 8,
  "isPositive": true
},
{
  "spin": 838,
  "isEven": false,
  "color": "red",
  "number": 21,
  "isPositive": true
},
{
  "spin": 839,
  "isEven": true,
  "color": "red",
  "number": 32,
  "isPositive": true
},
{
  "spin": 840,
  "isEven": true,
  "color": "red",
  "number": 36,
  "isPositive": true
},
{
  "spin": 841,
  "isEven": false,
  "color": "red",
  "number": 9,
  "isPositive": true
},
{
  "spin": 842,
  "isEven": false,
  "color": "red",
  "number": 1,
  "isPositive": true
},
{
  "spin": 843,
  "isEven": true,
  "color": "red",
  "number": 18,
  "isPositive": true
},
{
  "spin": 844,
  "isEven": false,
  "color": "red",
  "number": 3,
  "isPositive": true
},
{
  "spin": 845,
  "isEven": true,
  "color": "black",
  "number": 6,
  "isPositive": true
},
{
  "spin": 846,
  "isEven": true,
  "color": "black",
  "number": 20,
  "isPositive": true
},
{
  "spin": 847,
  "isEven": true,
  "color": "black",
  "number": 20,
  "isPositive": true
},
{
  "spin": 848,
  "isEven": true,
  "color": "black",
  "number": 26,
  "isPositive": true
},
{
  "spin": 849,
  "isEven": true,
  "color": "black",
  "number": 6,
  "isPositive": true
},
{
  "spin": 850,
  "isEven": false,
  "color": "black",
  "number": 13,
  "isPositive": true
},
{
  "spin": 851,
  "isEven": true,
  "color": "black",
  "number": 2,
  "isPositive": true
},
{
  "spin": 852,
  "isEven": true,
  "color": "red",
  "number": 34,
  "isPositive": true
},
{
  "spin": 853,
  "isEven": true,
  "color": "red",
  "number": 32,
  "isPositive": true
},
{
  "spin": 854,
  "isEven": false,
  "color": "red",
  "number": 21,
  "isPositive": true
},
{
  "spin": 855,
  "isEven": true,
  "color": "black",
  "number": 26,
  "isPositive": true
},
{
  "spin": 856,
  "isEven": false,
  "color": "red",
  "number": 23,
  "isPositive": true
},
{
  "spin": 857,
  "isEven": true,
  "color": "black",
  "number": 6,
  "isPositive": true
},
{
  "spin": 858,
  "isEven": true,
  "color": "black",
  "number": 4,
  "isPositive": true
},
{
  "spin": 859,
  "isEven": true,
  "color": "red",
  "number": 34,
  "isPositive": true
},
{
  "spin": 860,
  "isEven": false,
  "color": "black",
  "number": 31,
  "isPositive": true
},
{
  "spin": 861,
  "isEven": true,
  "color": "red",
  "number": 30,
  "isPositive": true
},
{
  "spin": 862,
  "isEven": true,
  "color": "red",
  "number": 30,
  "isPositive": true
},
{
  "spin": 863,
  "isEven": true,
  "color": "black",
  "number": 26,
  "isPositive": true
},
{
  "spin": 864,
  "isEven": false,
  "color": "red",
  "number": 1,
  "isPositive": true
},
{
  "spin": 865,
  "isEven": false,
  "color": "red",
  "number": 7,
  "isPositive": true
},
{
  "spin": 866,
  "isEven": true,
  "color": "black",
  "number": 26,
  "isPositive": true
},
{
  "spin": 867,
  "isEven": true,
  "color": "red",
  "number": 30,
  "isPositive": true
},
{
  "spin": 868,
  "isEven": false,
  "color": "black",
  "number": 13,
  "isPositive": true
},
{
  "spin": 869,
  "isEven": false,
  "color": "red",
  "number": 1,
  "isPositive": true
},
{
  "spin": 870,
  "isEven": false,
  "color": "red",
  "number": 21,
  "isPositive": true
},
{
  "spin": 871,
  "isEven": false,
  "color": "black",
  "number": 17,
  "isPositive": true
},
{
  "spin": 872,
  "isEven": false,
  "color": "black",
  "number": 15,
  "isPositive": true
},
{
  "spin": 873,
  "isEven": false,
  "color": "red",
  "number": 27,
  "isPositive": true
},
{
  "spin": 874,
  "isEven": false,
  "color": "red",
  "number": 27,
  "isPositive": true
},
{
  "spin": 875,
  "isEven": false,
  "color": "red",
  "number": 27,
  "isPositive": true
},
{
  "spin": 876,
  "isEven": true,
  "color": "red",
  "number": 12,
  "isPositive": true
},
{
  "spin": 877,
  "isEven": true,
  "color": "black",
  "number": 6,
  "isPositive": true
},
{
  "spin": 878,
  "isEven": false,
  "color": "red",
  "number": 5,
  "isPositive": true
},
{
  "spin": 879,
  "isEven": false,
  "color": "red",
  "number": 27,
  "isPositive": true
},
{
  "spin": 880,
  "isEven": false,
  "color": "red",
  "number": 1,
  "isPositive": true
},
{
  "spin": 881,
  "isEven": true,
  "color": "black",
  "number": 8,
  "isPositive": true
},
{
  "spin": 882,
  "isEven": false,
  "color": "black",
  "number": 35,
  "isPositive": true
},
{
  "spin": 883,
  "isEven": false,
  "color": "red",
  "number": 23,
  "isPositive": true
},
{
  "spin": 884,
  "isEven": true,
  "color": "black",
  "number": 26,
  "isPositive": true
},
{
  "spin": 885,
  "isEven": true,
  "color": "black",
  "number": 6,
  "isPositive": true
},
{
  "spin": 886,
  "isEven": true,
  "color": "red",
  "number": 32,
  "isPositive": true
},
{
  "spin": 887,
  "isEven": true,
  "color": "red",
  "number": 34,
  "isPositive": true
},
{
  "spin": 888,
  "isEven": false,
  "color": "red",
  "number": 23,
  "isPositive": true
},
{
  "spin": 889,
  "isEven": false,
  "color": "black",
  "number": 17,
  "isPositive": true
},
{
  "spin": 890,
  "isEven": true,
  "color": "red",
  "number": 34,
  "isPositive": true
},
{
  "spin": 891,
  "isEven": false,
  "color": "red",
  "number": 5,
  "isPositive": true
},
{
  "spin": 892,
  "isEven": true,
  "color": "red",
  "number": 30,
  "isPositive": true
},
{
  "spin": 893,
  "isEven": false,
  "color": "red",
  "number": 9,
  "isPositive": true
},
{
  "spin": 894,
  "isEven": true,
  "color": "red",
  "number": 12,
  "isPositive": true
},
{
  "spin": 895,
  "isEven": true,
  "color": "red",
  "number": 32,
  "isPositive": true
},
{
  "spin": 896,
  "isEven": true,
  "color": "red",
  "number": 18,
  "isPositive": true
},
{
  "spin": 897,
  "isEven": true,
  "color": "black",
  "number": 10,
  "isPositive": true
},
{
  "spin": 898,
  "isEven": true,
  "color": "black",
  "number": 28,
  "isPositive": true
},
{
  "spin": 899,
  "isEven": false,
  "color": "red",
  "number": 9,
  "isPositive": true
},
{
  "spin": 900,
  "isEven": true,
  "color": "black",
  "number": 6,
  "isPositive": true
},
